{"_path":"/frontend-code-assessment/scene/countdown","_dir":"scene","_draft":false,"_partial":false,"_locale":"","title":"倒计时","description":"","body":{"type":"root","children":[{"type":"element","tag":"pre","props":{"className":"language-js shiki shiki-themes slack-ochin slack-ochin ayu-dark","code":"const totalDuration = 10 * 1000;\nlet requestRef = null;\nlet startTime;\nlet prevEndTime;\nlet prevTime;\nlet currentCount = totalDuration;\nlet endTime;\nlet timeDiffer = 0; // 每1s倒计时偏差值，单位ms\nlet interval = 1000;\nlet nextTime = interval;\n\nsetInterval(() => {\n  let n = 0;\n  while (n++ < 1000000000);\n}, 0);\n\nconst animate = (timestamp) => {\n  if (prevTime !== undefined) {\n    const deltaTime = timestamp - prevTime;\n    if (deltaTime >= nextTime) {\n      prevTime = timestamp;\n      prevEndTime = endTime;\n      endTime = new Date().getTime();\n      currentCount = currentCount - 1000;\n      console.log(\"currentCount: \", currentCount / 1000);\n      timeDiffer = endTime - startTime - (totalDuration - currentCount);\n      console.log(timeDiffer);\n      nextTime = interval - timeDiffer;\n      // 慢太多了，就立刻执行下一个循环\n      if (nextTime < 0) {\n        nextTime = 0;\n      }\n      console.log(`执行下一次渲染的时间是：${nextTime}ms`);\n      if (currentCount <= 0) {\n        currentCount = 0;\n        cancelAnimationFrame(requestRef);\n        console.log(`累计偏差值： ${endTime - startTime - totalDuration}ms`);\n        return;\n      }\n    }\n  } else {\n    startTime = new Date().getTime();\n    prevTime = timestamp;\n    endTime = new Date().getTime();\n  }\n  requestRef = requestAnimationFrame(animate);\n};\n\nrequestRef = requestAnimationFrame(animate);\n","language":"js","meta":"","style":""},"children":[{"type":"element","tag":"code","props":{"__ignoreMap":""},"children":[{"type":"element","tag":"span","props":{"class":"line","line":1},"children":[{"type":"element","tag":"span","props":{"style":"--shiki-light:#0991B6;--shiki-default:#0991B6;--shiki-dark:#FF8F40"},"children":[{"type":"text","value":"const"}]},{"type":"element","tag":"span","props":{"style":"--shiki-light:#2F86D2;--shiki-default:#2F86D2;--shiki-dark:#BFBDB6"},"children":[{"type":"text","value":" totalDuration"}]},{"type":"element","tag":"span","props":{"style":"--shiki-light:#7B30D0;--shiki-default:#7B30D0;--shiki-dark:#F29668"},"children":[{"type":"text","value":" ="}]},{"type":"element","tag":"span","props":{"style":"--shiki-light:#174781;--shiki-default:#174781;--shiki-dark:#D2A6FF"},"children":[{"type":"text","value":" 10"}]},{"type":"element","tag":"span","props":{"style":"--shiki-light:#7B30D0;--shiki-default:#7B30D0;--shiki-dark:#F29668"},"children":[{"type":"text","value":" *"}]},{"type":"element","tag":"span","props":{"style":"--shiki-light:#174781;--shiki-default:#174781;--shiki-dark:#D2A6FF"},"children":[{"type":"text","value":" 1000"}]},{"type":"element","tag":"span","props":{"style":"--shiki-light:#002339;--shiki-default:#002339;--shiki-dark:#BFBDB6B3"},"children":[{"type":"text","value":";\n"}]}]},{"type":"element","tag":"span","props":{"class":"line","line":2},"children":[{"type":"element","tag":"span","props":{"style":"--shiki-light:#0991B6;--shiki-default:#0991B6;--shiki-dark:#FF8F40"},"children":[{"type":"text","value":"let"}]},{"type":"element","tag":"span","props":{"style":"--shiki-light:#2F86D2;--shiki-default:#2F86D2;--shiki-dark:#BFBDB6"},"children":[{"type":"text","value":" requestRef"}]},{"type":"element","tag":"span","props":{"style":"--shiki-light:#7B30D0;--shiki-default:#7B30D0;--shiki-dark:#F29668"},"children":[{"type":"text","value":" ="}]},{"type":"element","tag":"span","props":{"style":"--shiki-light:#174781;--shiki-default:#174781;--shiki-dark:#D2A6FF"},"children":[{"type":"text","value":" null"}]},{"type":"element","tag":"span","props":{"style":"--shiki-light:#002339;--shiki-default:#002339;--shiki-dark:#BFBDB6B3"},"children":[{"type":"text","value":";\n"}]}]},{"type":"element","tag":"span","props":{"class":"line","line":3},"children":[{"type":"element","tag":"span","props":{"style":"--shiki-light:#0991B6;--shiki-default:#0991B6;--shiki-dark:#FF8F40"},"children":[{"type":"text","value":"let"}]},{"type":"element","tag":"span","props":{"style":"--shiki-light:#2F86D2;--shiki-default:#2F86D2;--shiki-dark:#BFBDB6"},"children":[{"type":"text","value":" startTime"}]},{"type":"element","tag":"span","props":{"style":"--shiki-light:#002339;--shiki-default:#002339;--shiki-dark:#BFBDB6B3"},"children":[{"type":"text","value":";\n"}]}]},{"type":"element","tag":"span","props":{"class":"line","line":4},"children":[{"type":"element","tag":"span","props":{"style":"--shiki-light:#0991B6;--shiki-default:#0991B6;--shiki-dark:#FF8F40"},"children":[{"type":"text","value":"let"}]},{"type":"element","tag":"span","props":{"style":"--shiki-light:#2F86D2;--shiki-default:#2F86D2;--shiki-dark:#BFBDB6"},"children":[{"type":"text","value":" prevEndTime"}]},{"type":"element","tag":"span","props":{"style":"--shiki-light:#002339;--shiki-default:#002339;--shiki-dark:#BFBDB6B3"},"children":[{"type":"text","value":";\n"}]}]},{"type":"element","tag":"span","props":{"class":"line","line":5},"children":[{"type":"element","tag":"span","props":{"style":"--shiki-light:#0991B6;--shiki-default:#0991B6;--shiki-dark:#FF8F40"},"children":[{"type":"text","value":"let"}]},{"type":"element","tag":"span","props":{"style":"--shiki-light:#2F86D2;--shiki-default:#2F86D2;--shiki-dark:#BFBDB6"},"children":[{"type":"text","value":" prevTime"}]},{"type":"element","tag":"span","props":{"style":"--shiki-light:#002339;--shiki-default:#002339;--shiki-dark:#BFBDB6B3"},"children":[{"type":"text","value":";\n"}]}]},{"type":"element","tag":"span","props":{"class":"line","line":6},"children":[{"type":"element","tag":"span","props":{"style":"--shiki-light:#0991B6;--shiki-default:#0991B6;--shiki-dark:#FF8F40"},"children":[{"type":"text","value":"let"}]},{"type":"element","tag":"span","props":{"style":"--shiki-light:#2F86D2;--shiki-default:#2F86D2;--shiki-dark:#BFBDB6"},"children":[{"type":"text","value":" currentCount"}]},{"type":"element","tag":"span","props":{"style":"--shiki-light:#7B30D0;--shiki-default:#7B30D0;--shiki-dark:#F29668"},"children":[{"type":"text","value":" ="}]},{"type":"element","tag":"span","props":{"style":"--shiki-light:#2F86D2;--shiki-default:#2F86D2;--shiki-dark:#BFBDB6"},"children":[{"type":"text","value":" totalDuration"}]},{"type":"element","tag":"span","props":{"style":"--shiki-light:#002339;--shiki-default:#002339;--shiki-dark:#BFBDB6B3"},"children":[{"type":"text","value":";\n"}]}]},{"type":"element","tag":"span","props":{"class":"line","line":7},"children":[{"type":"element","tag":"span","props":{"style":"--shiki-light:#0991B6;--shiki-default:#0991B6;--shiki-dark:#FF8F40"},"children":[{"type":"text","value":"let"}]},{"type":"element","tag":"span","props":{"style":"--shiki-light:#2F86D2;--shiki-default:#2F86D2;--shiki-dark:#BFBDB6"},"children":[{"type":"text","value":" endTime"}]},{"type":"element","tag":"span","props":{"style":"--shiki-light:#002339;--shiki-default:#002339;--shiki-dark:#BFBDB6B3"},"children":[{"type":"text","value":";\n"}]}]},{"type":"element","tag":"span","props":{"class":"line","line":8},"children":[{"type":"element","tag":"span","props":{"style":"--shiki-light:#0991B6;--shiki-default:#0991B6;--shiki-dark:#FF8F40"},"children":[{"type":"text","value":"let"}]},{"type":"element","tag":"span","props":{"style":"--shiki-light:#2F86D2;--shiki-default:#2F86D2;--shiki-dark:#BFBDB6"},"children":[{"type":"text","value":" timeDiffer"}]},{"type":"element","tag":"span","props":{"style":"--shiki-light:#7B30D0;--shiki-default:#7B30D0;--shiki-dark:#F29668"},"children":[{"type":"text","value":" ="}]},{"type":"element","tag":"span","props":{"style":"--shiki-light:#174781;--shiki-default:#174781;--shiki-dark:#D2A6FF"},"children":[{"type":"text","value":" 0"}]},{"type":"element","tag":"span","props":{"style":"--shiki-light:#002339;--shiki-default:#002339;--shiki-dark:#BFBDB6B3"},"children":[{"type":"text","value":";"}]},{"type":"element","tag":"span","props":{"style":"--shiki-light:#357B42;--shiki-default:#357B42;--shiki-dark:#ACB6BF8C;--shiki-light-font-style:italic;--shiki-default-font-style:italic;--shiki-dark-font-style:italic"},"children":[{"type":"text","value":" // 每1s倒计时偏差值，单位ms\n"}]}]},{"type":"element","tag":"span","props":{"class":"line","line":9},"children":[{"type":"element","tag":"span","props":{"style":"--shiki-light:#0991B6;--shiki-default:#0991B6;--shiki-dark:#FF8F40"},"children":[{"type":"text","value":"let"}]},{"type":"element","tag":"span","props":{"style":"--shiki-light:#2F86D2;--shiki-default:#2F86D2;--shiki-dark:#BFBDB6"},"children":[{"type":"text","value":" interval"}]},{"type":"element","tag":"span","props":{"style":"--shiki-light:#7B30D0;--shiki-default:#7B30D0;--shiki-dark:#F29668"},"children":[{"type":"text","value":" ="}]},{"type":"element","tag":"span","props":{"style":"--shiki-light:#174781;--shiki-default:#174781;--shiki-dark:#D2A6FF"},"children":[{"type":"text","value":" 1000"}]},{"type":"element","tag":"span","props":{"style":"--shiki-light:#002339;--shiki-default:#002339;--shiki-dark:#BFBDB6B3"},"children":[{"type":"text","value":";\n"}]}]},{"type":"element","tag":"span","props":{"class":"line","line":10},"children":[{"type":"element","tag":"span","props":{"style":"--shiki-light:#0991B6;--shiki-default:#0991B6;--shiki-dark:#FF8F40"},"children":[{"type":"text","value":"let"}]},{"type":"element","tag":"span","props":{"style":"--shiki-light:#2F86D2;--shiki-default:#2F86D2;--shiki-dark:#BFBDB6"},"children":[{"type":"text","value":" nextTime"}]},{"type":"element","tag":"span","props":{"style":"--shiki-light:#7B30D0;--shiki-default:#7B30D0;--shiki-dark:#F29668"},"children":[{"type":"text","value":" ="}]},{"type":"element","tag":"span","props":{"style":"--shiki-light:#2F86D2;--shiki-default:#2F86D2;--shiki-dark:#BFBDB6"},"children":[{"type":"text","value":" interval"}]},{"type":"element","tag":"span","props":{"style":"--shiki-light:#002339;--shiki-default:#002339;--shiki-dark:#BFBDB6B3"},"children":[{"type":"text","value":";\n"}]}]},{"type":"element","tag":"span","props":{"class":"line","line":11},"children":[{"type":"element","tag":"span","props":{"emptyLinePlaceholder":true},"children":[{"type":"text","value":"\n"}]}]},{"type":"element","tag":"span","props":{"class":"line","line":12},"children":[{"type":"element","tag":"span","props":{"style":"--shiki-light:#7EB233;--shiki-default:#7EB233;--shiki-dark:#FFB454"},"children":[{"type":"text","value":"setInterval"}]},{"type":"element","tag":"span","props":{"style":"--shiki-light:#002339;--shiki-default:#002339;--shiki-dark:#BFBDB6"},"children":[{"type":"text","value":"(() "}]},{"type":"element","tag":"span","props":{"style":"--shiki-light:#0991B6;--shiki-default:#0991B6;--shiki-dark:#FF8F40"},"children":[{"type":"text","value":"=>"}]},{"type":"element","tag":"span","props":{"style":"--shiki-light:#002339;--shiki-default:#002339;--shiki-dark:#BFBDB6"},"children":[{"type":"text","value":" {\n"}]}]},{"type":"element","tag":"span","props":{"class":"line","line":13},"children":[{"type":"element","tag":"span","props":{"style":"--shiki-light:#0991B6;--shiki-default:#0991B6;--shiki-dark:#FF8F40"},"children":[{"type":"text","value":"  let"}]},{"type":"element","tag":"span","props":{"style":"--shiki-light:#2F86D2;--shiki-default:#2F86D2;--shiki-dark:#BFBDB6"},"children":[{"type":"text","value":" n"}]},{"type":"element","tag":"span","props":{"style":"--shiki-light:#7B30D0;--shiki-default:#7B30D0;--shiki-dark:#F29668"},"children":[{"type":"text","value":" ="}]},{"type":"element","tag":"span","props":{"style":"--shiki-light:#174781;--shiki-default:#174781;--shiki-dark:#D2A6FF"},"children":[{"type":"text","value":" 0"}]},{"type":"element","tag":"span","props":{"style":"--shiki-light:#002339;--shiki-default:#002339;--shiki-dark:#BFBDB6B3"},"children":[{"type":"text","value":";\n"}]}]},{"type":"element","tag":"span","props":{"class":"line","line":14},"children":[{"type":"element","tag":"span","props":{"style":"--shiki-light:#7B30D0;--shiki-default:#7B30D0;--shiki-dark:#FF8F40"},"children":[{"type":"text","value":"  while"}]},{"type":"element","tag":"span","props":{"style":"--shiki-light:#002339;--shiki-default:#002339;--shiki-dark:#BFBDB6"},"children":[{"type":"text","value":" ("}]},{"type":"element","tag":"span","props":{"style":"--shiki-light:#2F86D2;--shiki-default:#2F86D2;--shiki-dark:#BFBDB6"},"children":[{"type":"text","value":"n"}]},{"type":"element","tag":"span","props":{"style":"--shiki-light:#7B30D0;--shiki-default:#7B30D0;--shiki-dark:#F29668"},"children":[{"type":"text","value":"++"}]},{"type":"element","tag":"span","props":{"style":"--shiki-light:#7B30D0;--shiki-default:#7B30D0;--shiki-dark:#F29668"},"children":[{"type":"text","value":" <"}]},{"type":"element","tag":"span","props":{"style":"--shiki-light:#174781;--shiki-default:#174781;--shiki-dark:#D2A6FF"},"children":[{"type":"text","value":" 1000000000"}]},{"type":"element","tag":"span","props":{"style":"--shiki-light:#002339;--shiki-default:#002339;--shiki-dark:#BFBDB6"},"children":[{"type":"text","value":")"}]},{"type":"element","tag":"span","props":{"style":"--shiki-light:#002339;--shiki-default:#002339;--shiki-dark:#BFBDB6B3"},"children":[{"type":"text","value":";\n"}]}]},{"type":"element","tag":"span","props":{"class":"line","line":15},"children":[{"type":"element","tag":"span","props":{"style":"--shiki-light:#002339;--shiki-default:#002339;--shiki-dark:#BFBDB6"},"children":[{"type":"text","value":"}"}]},{"type":"element","tag":"span","props":{"style":"--shiki-light:#002339;--shiki-default:#002339;--shiki-dark:#BFBDB6B3"},"children":[{"type":"text","value":","}]},{"type":"element","tag":"span","props":{"style":"--shiki-light:#174781;--shiki-default:#174781;--shiki-dark:#D2A6FF"},"children":[{"type":"text","value":" 0"}]},{"type":"element","tag":"span","props":{"style":"--shiki-light:#002339;--shiki-default:#002339;--shiki-dark:#BFBDB6"},"children":[{"type":"text","value":")"}]},{"type":"element","tag":"span","props":{"style":"--shiki-light:#002339;--shiki-default:#002339;--shiki-dark:#BFBDB6B3"},"children":[{"type":"text","value":";\n"}]}]},{"type":"element","tag":"span","props":{"class":"line","line":16},"children":[{"type":"element","tag":"span","props":{"emptyLinePlaceholder":true},"children":[{"type":"text","value":"\n"}]}]},{"type":"element","tag":"span","props":{"class":"line","line":17},"children":[{"type":"element","tag":"span","props":{"style":"--shiki-light:#0991B6;--shiki-default:#0991B6;--shiki-dark:#FF8F40"},"children":[{"type":"text","value":"const"}]},{"type":"element","tag":"span","props":{"style":"--shiki-light:#7EB233;--shiki-default:#7EB233;--shiki-dark:#FFB454"},"children":[{"type":"text","value":" animate"}]},{"type":"element","tag":"span","props":{"style":"--shiki-light:#7B30D0;--shiki-default:#7B30D0;--shiki-dark:#F29668"},"children":[{"type":"text","value":" ="}]},{"type":"element","tag":"span","props":{"style":"--shiki-light:#002339;--shiki-default:#002339;--shiki-dark:#BFBDB6"},"children":[{"type":"text","value":" ("}]},{"type":"element","tag":"span","props":{"style":"--shiki-light:#B1108E;--shiki-default:#B1108E;--shiki-dark:#D2A6FF"},"children":[{"type":"text","value":"timestamp"}]},{"type":"element","tag":"span","props":{"style":"--shiki-light:#002339;--shiki-default:#002339;--shiki-dark:#BFBDB6"},"children":[{"type":"text","value":") "}]},{"type":"element","tag":"span","props":{"style":"--shiki-light:#0991B6;--shiki-default:#0991B6;--shiki-dark:#FF8F40"},"children":[{"type":"text","value":"=>"}]},{"type":"element","tag":"span","props":{"style":"--shiki-light:#002339;--shiki-default:#002339;--shiki-dark:#BFBDB6"},"children":[{"type":"text","value":" {\n"}]}]},{"type":"element","tag":"span","props":{"class":"line","line":18},"children":[{"type":"element","tag":"span","props":{"style":"--shiki-light:#7B30D0;--shiki-default:#7B30D0;--shiki-dark:#FF8F40"},"children":[{"type":"text","value":"  if"}]},{"type":"element","tag":"span","props":{"style":"--shiki-light:#002339;--shiki-default:#002339;--shiki-dark:#BFBDB6"},"children":[{"type":"text","value":" ("}]},{"type":"element","tag":"span","props":{"style":"--shiki-light:#2F86D2;--shiki-default:#2F86D2;--shiki-dark:#BFBDB6"},"children":[{"type":"text","value":"prevTime"}]},{"type":"element","tag":"span","props":{"style":"--shiki-light:#7B30D0;--shiki-default:#7B30D0;--shiki-dark:#F29668"},"children":[{"type":"text","value":" !=="}]},{"type":"element","tag":"span","props":{"style":"--shiki-light:#174781;--shiki-default:#174781;--shiki-dark:#D2A6FF"},"children":[{"type":"text","value":" undefined"}]},{"type":"element","tag":"span","props":{"style":"--shiki-light:#002339;--shiki-default:#002339;--shiki-dark:#BFBDB6"},"children":[{"type":"text","value":") {\n"}]}]},{"type":"element","tag":"span","props":{"class":"line","line":19},"children":[{"type":"element","tag":"span","props":{"style":"--shiki-light:#0991B6;--shiki-default:#0991B6;--shiki-dark:#FF8F40"},"children":[{"type":"text","value":"    const"}]},{"type":"element","tag":"span","props":{"style":"--shiki-light:#2F86D2;--shiki-default:#2F86D2;--shiki-dark:#BFBDB6"},"children":[{"type":"text","value":" deltaTime"}]},{"type":"element","tag":"span","props":{"style":"--shiki-light:#7B30D0;--shiki-default:#7B30D0;--shiki-dark:#F29668"},"children":[{"type":"text","value":" ="}]},{"type":"element","tag":"span","props":{"style":"--shiki-light:#2F86D2;--shiki-default:#2F86D2;--shiki-dark:#BFBDB6"},"children":[{"type":"text","value":" timestamp"}]},{"type":"element","tag":"span","props":{"style":"--shiki-light:#7B30D0;--shiki-default:#7B30D0;--shiki-dark:#F29668"},"children":[{"type":"text","value":" -"}]},{"type":"element","tag":"span","props":{"style":"--shiki-light:#2F86D2;--shiki-default:#2F86D2;--shiki-dark:#BFBDB6"},"children":[{"type":"text","value":" prevTime"}]},{"type":"element","tag":"span","props":{"style":"--shiki-light:#002339;--shiki-default:#002339;--shiki-dark:#BFBDB6B3"},"children":[{"type":"text","value":";\n"}]}]},{"type":"element","tag":"span","props":{"class":"line","line":20},"children":[{"type":"element","tag":"span","props":{"style":"--shiki-light:#7B30D0;--shiki-default:#7B30D0;--shiki-dark:#FF8F40"},"children":[{"type":"text","value":"    if"}]},{"type":"element","tag":"span","props":{"style":"--shiki-light:#002339;--shiki-default:#002339;--shiki-dark:#BFBDB6"},"children":[{"type":"text","value":" ("}]},{"type":"element","tag":"span","props":{"style":"--shiki-light:#2F86D2;--shiki-default:#2F86D2;--shiki-dark:#BFBDB6"},"children":[{"type":"text","value":"deltaTime"}]},{"type":"element","tag":"span","props":{"style":"--shiki-light:#7B30D0;--shiki-default:#7B30D0;--shiki-dark:#F29668"},"children":[{"type":"text","value":" >="}]},{"type":"element","tag":"span","props":{"style":"--shiki-light:#2F86D2;--shiki-default:#2F86D2;--shiki-dark:#BFBDB6"},"children":[{"type":"text","value":" nextTime"}]},{"type":"element","tag":"span","props":{"style":"--shiki-light:#002339;--shiki-default:#002339;--shiki-dark:#BFBDB6"},"children":[{"type":"text","value":") {\n"}]}]},{"type":"element","tag":"span","props":{"class":"line","line":21},"children":[{"type":"element","tag":"span","props":{"style":"--shiki-light:#2F86D2;--shiki-default:#2F86D2;--shiki-dark:#BFBDB6"},"children":[{"type":"text","value":"      prevTime"}]},{"type":"element","tag":"span","props":{"style":"--shiki-light:#7B30D0;--shiki-default:#7B30D0;--shiki-dark:#F29668"},"children":[{"type":"text","value":" ="}]},{"type":"element","tag":"span","props":{"style":"--shiki-light:#2F86D2;--shiki-default:#2F86D2;--shiki-dark:#BFBDB6"},"children":[{"type":"text","value":" timestamp"}]},{"type":"element","tag":"span","props":{"style":"--shiki-light:#002339;--shiki-default:#002339;--shiki-dark:#BFBDB6B3"},"children":[{"type":"text","value":";\n"}]}]},{"type":"element","tag":"span","props":{"class":"line","line":22},"children":[{"type":"element","tag":"span","props":{"style":"--shiki-light:#2F86D2;--shiki-default:#2F86D2;--shiki-dark:#BFBDB6"},"children":[{"type":"text","value":"      prevEndTime"}]},{"type":"element","tag":"span","props":{"style":"--shiki-light:#7B30D0;--shiki-default:#7B30D0;--shiki-dark:#F29668"},"children":[{"type":"text","value":" ="}]},{"type":"element","tag":"span","props":{"style":"--shiki-light:#2F86D2;--shiki-default:#2F86D2;--shiki-dark:#BFBDB6"},"children":[{"type":"text","value":" endTime"}]},{"type":"element","tag":"span","props":{"style":"--shiki-light:#002339;--shiki-default:#002339;--shiki-dark:#BFBDB6B3"},"children":[{"type":"text","value":";\n"}]}]},{"type":"element","tag":"span","props":{"class":"line","line":23},"children":[{"type":"element","tag":"span","props":{"style":"--shiki-light:#2F86D2;--shiki-default:#2F86D2;--shiki-dark:#BFBDB6"},"children":[{"type":"text","value":"      endTime"}]},{"type":"element","tag":"span","props":{"style":"--shiki-light:#7B30D0;--shiki-default:#7B30D0;--shiki-dark:#F29668"},"children":[{"type":"text","value":" ="}]},{"type":"element","tag":"span","props":{"style":"--shiki-light:#7B30D0;--shiki-default:#7B30D0;--shiki-dark:#F29668"},"children":[{"type":"text","value":" new"}]},{"type":"element","tag":"span","props":{"style":"--shiki-light:#7EB233;--shiki-default:#7EB233;--shiki-dark:#FFB454"},"children":[{"type":"text","value":" Date"}]},{"type":"element","tag":"span","props":{"style":"--shiki-light:#002339;--shiki-default:#002339;--shiki-dark:#BFBDB6"},"children":[{"type":"text","value":"()"}]},{"type":"element","tag":"span","props":{"style":"--shiki-light:#002339;--shiki-default:#002339;--shiki-dark:#F29668"},"children":[{"type":"text","value":"."}]},{"type":"element","tag":"span","props":{"style":"--shiki-light:#7EB233;--shiki-default:#7EB233;--shiki-dark:#FFB454"},"children":[{"type":"text","value":"getTime"}]},{"type":"element","tag":"span","props":{"style":"--shiki-light:#002339;--shiki-default:#002339;--shiki-dark:#BFBDB6"},"children":[{"type":"text","value":"()"}]},{"type":"element","tag":"span","props":{"style":"--shiki-light:#002339;--shiki-default:#002339;--shiki-dark:#BFBDB6B3"},"children":[{"type":"text","value":";\n"}]}]},{"type":"element","tag":"span","props":{"class":"line","line":24},"children":[{"type":"element","tag":"span","props":{"style":"--shiki-light:#2F86D2;--shiki-default:#2F86D2;--shiki-dark:#BFBDB6"},"children":[{"type":"text","value":"      currentCount"}]},{"type":"element","tag":"span","props":{"style":"--shiki-light:#7B30D0;--shiki-default:#7B30D0;--shiki-dark:#F29668"},"children":[{"type":"text","value":" ="}]},{"type":"element","tag":"span","props":{"style":"--shiki-light:#2F86D2;--shiki-default:#2F86D2;--shiki-dark:#BFBDB6"},"children":[{"type":"text","value":" currentCount"}]},{"type":"element","tag":"span","props":{"style":"--shiki-light:#7B30D0;--shiki-default:#7B30D0;--shiki-dark:#F29668"},"children":[{"type":"text","value":" -"}]},{"type":"element","tag":"span","props":{"style":"--shiki-light:#174781;--shiki-default:#174781;--shiki-dark:#D2A6FF"},"children":[{"type":"text","value":" 1000"}]},{"type":"element","tag":"span","props":{"style":"--shiki-light:#002339;--shiki-default:#002339;--shiki-dark:#BFBDB6B3"},"children":[{"type":"text","value":";\n"}]}]},{"type":"element","tag":"span","props":{"class":"line","line":25},"children":[{"type":"element","tag":"span","props":{"style":"--shiki-light:#2F86D2;--shiki-default:#2F86D2;--shiki-dark:#BFBDB6"},"children":[{"type":"text","value":"      console"}]},{"type":"element","tag":"span","props":{"style":"--shiki-light:#002339;--shiki-default:#002339;--shiki-dark:#F29668"},"children":[{"type":"text","value":"."}]},{"type":"element","tag":"span","props":{"style":"--shiki-light:#7EB233;--shiki-default:#7EB233;--shiki-dark:#FFB454"},"children":[{"type":"text","value":"log"}]},{"type":"element","tag":"span","props":{"style":"--shiki-light:#002339;--shiki-default:#002339;--shiki-dark:#BFBDB6"},"children":[{"type":"text","value":"("}]},{"type":"element","tag":"span","props":{"style":"--shiki-light:#A44185;--shiki-default:#A44185;--shiki-dark:#AAD94C"},"children":[{"type":"text","value":"\"currentCount: \""}]},{"type":"element","tag":"span","props":{"style":"--shiki-light:#002339;--shiki-default:#002339;--shiki-dark:#BFBDB6B3"},"children":[{"type":"text","value":","}]},{"type":"element","tag":"span","props":{"style":"--shiki-light:#2F86D2;--shiki-default:#2F86D2;--shiki-dark:#BFBDB6"},"children":[{"type":"text","value":" currentCount"}]},{"type":"element","tag":"span","props":{"style":"--shiki-light:#7B30D0;--shiki-default:#7B30D0;--shiki-dark:#F29668"},"children":[{"type":"text","value":" /"}]},{"type":"element","tag":"span","props":{"style":"--shiki-light:#174781;--shiki-default:#174781;--shiki-dark:#D2A6FF"},"children":[{"type":"text","value":" 1000"}]},{"type":"element","tag":"span","props":{"style":"--shiki-light:#002339;--shiki-default:#002339;--shiki-dark:#BFBDB6"},"children":[{"type":"text","value":")"}]},{"type":"element","tag":"span","props":{"style":"--shiki-light:#002339;--shiki-default:#002339;--shiki-dark:#BFBDB6B3"},"children":[{"type":"text","value":";\n"}]}]},{"type":"element","tag":"span","props":{"class":"line","line":26},"children":[{"type":"element","tag":"span","props":{"style":"--shiki-light:#2F86D2;--shiki-default:#2F86D2;--shiki-dark:#BFBDB6"},"children":[{"type":"text","value":"      timeDiffer"}]},{"type":"element","tag":"span","props":{"style":"--shiki-light:#7B30D0;--shiki-default:#7B30D0;--shiki-dark:#F29668"},"children":[{"type":"text","value":" ="}]},{"type":"element","tag":"span","props":{"style":"--shiki-light:#2F86D2;--shiki-default:#2F86D2;--shiki-dark:#BFBDB6"},"children":[{"type":"text","value":" endTime"}]},{"type":"element","tag":"span","props":{"style":"--shiki-light:#7B30D0;--shiki-default:#7B30D0;--shiki-dark:#F29668"},"children":[{"type":"text","value":" -"}]},{"type":"element","tag":"span","props":{"style":"--shiki-light:#2F86D2;--shiki-default:#2F86D2;--shiki-dark:#BFBDB6"},"children":[{"type":"text","value":" startTime"}]},{"type":"element","tag":"span","props":{"style":"--shiki-light:#7B30D0;--shiki-default:#7B30D0;--shiki-dark:#F29668"},"children":[{"type":"text","value":" -"}]},{"type":"element","tag":"span","props":{"style":"--shiki-light:#002339;--shiki-default:#002339;--shiki-dark:#BFBDB6"},"children":[{"type":"text","value":" ("}]},{"type":"element","tag":"span","props":{"style":"--shiki-light:#2F86D2;--shiki-default:#2F86D2;--shiki-dark:#BFBDB6"},"children":[{"type":"text","value":"totalDuration"}]},{"type":"element","tag":"span","props":{"style":"--shiki-light:#7B30D0;--shiki-default:#7B30D0;--shiki-dark:#F29668"},"children":[{"type":"text","value":" -"}]},{"type":"element","tag":"span","props":{"style":"--shiki-light:#2F86D2;--shiki-default:#2F86D2;--shiki-dark:#BFBDB6"},"children":[{"type":"text","value":" currentCount"}]},{"type":"element","tag":"span","props":{"style":"--shiki-light:#002339;--shiki-default:#002339;--shiki-dark:#BFBDB6"},"children":[{"type":"text","value":")"}]},{"type":"element","tag":"span","props":{"style":"--shiki-light:#002339;--shiki-default:#002339;--shiki-dark:#BFBDB6B3"},"children":[{"type":"text","value":";\n"}]}]},{"type":"element","tag":"span","props":{"class":"line","line":27},"children":[{"type":"element","tag":"span","props":{"style":"--shiki-light:#2F86D2;--shiki-default:#2F86D2;--shiki-dark:#BFBDB6"},"children":[{"type":"text","value":"      console"}]},{"type":"element","tag":"span","props":{"style":"--shiki-light:#002339;--shiki-default:#002339;--shiki-dark:#F29668"},"children":[{"type":"text","value":"."}]},{"type":"element","tag":"span","props":{"style":"--shiki-light:#7EB233;--shiki-default:#7EB233;--shiki-dark:#FFB454"},"children":[{"type":"text","value":"log"}]},{"type":"element","tag":"span","props":{"style":"--shiki-light:#002339;--shiki-default:#002339;--shiki-dark:#BFBDB6"},"children":[{"type":"text","value":"("}]},{"type":"element","tag":"span","props":{"style":"--shiki-light:#2F86D2;--shiki-default:#2F86D2;--shiki-dark:#BFBDB6"},"children":[{"type":"text","value":"timeDiffer"}]},{"type":"element","tag":"span","props":{"style":"--shiki-light:#002339;--shiki-default:#002339;--shiki-dark:#BFBDB6"},"children":[{"type":"text","value":")"}]},{"type":"element","tag":"span","props":{"style":"--shiki-light:#002339;--shiki-default:#002339;--shiki-dark:#BFBDB6B3"},"children":[{"type":"text","value":";\n"}]}]},{"type":"element","tag":"span","props":{"class":"line","line":28},"children":[{"type":"element","tag":"span","props":{"style":"--shiki-light:#2F86D2;--shiki-default:#2F86D2;--shiki-dark:#BFBDB6"},"children":[{"type":"text","value":"      nextTime"}]},{"type":"element","tag":"span","props":{"style":"--shiki-light:#7B30D0;--shiki-default:#7B30D0;--shiki-dark:#F29668"},"children":[{"type":"text","value":" ="}]},{"type":"element","tag":"span","props":{"style":"--shiki-light:#2F86D2;--shiki-default:#2F86D2;--shiki-dark:#BFBDB6"},"children":[{"type":"text","value":" interval"}]},{"type":"element","tag":"span","props":{"style":"--shiki-light:#7B30D0;--shiki-default:#7B30D0;--shiki-dark:#F29668"},"children":[{"type":"text","value":" -"}]},{"type":"element","tag":"span","props":{"style":"--shiki-light:#2F86D2;--shiki-default:#2F86D2;--shiki-dark:#BFBDB6"},"children":[{"type":"text","value":" timeDiffer"}]},{"type":"element","tag":"span","props":{"style":"--shiki-light:#002339;--shiki-default:#002339;--shiki-dark:#BFBDB6B3"},"children":[{"type":"text","value":";\n"}]}]},{"type":"element","tag":"span","props":{"class":"line","line":29},"children":[{"type":"element","tag":"span","props":{"style":"--shiki-light:#357B42;--shiki-default:#357B42;--shiki-dark:#ACB6BF8C;--shiki-light-font-style:italic;--shiki-default-font-style:italic;--shiki-dark-font-style:italic"},"children":[{"type":"text","value":"      // 慢太多了，就立刻执行下一个循环\n"}]}]},{"type":"element","tag":"span","props":{"class":"line","line":30},"children":[{"type":"element","tag":"span","props":{"style":"--shiki-light:#7B30D0;--shiki-default:#7B30D0;--shiki-dark:#FF8F40"},"children":[{"type":"text","value":"      if"}]},{"type":"element","tag":"span","props":{"style":"--shiki-light:#002339;--shiki-default:#002339;--shiki-dark:#BFBDB6"},"children":[{"type":"text","value":" ("}]},{"type":"element","tag":"span","props":{"style":"--shiki-light:#2F86D2;--shiki-default:#2F86D2;--shiki-dark:#BFBDB6"},"children":[{"type":"text","value":"nextTime"}]},{"type":"element","tag":"span","props":{"style":"--shiki-light:#7B30D0;--shiki-default:#7B30D0;--shiki-dark:#F29668"},"children":[{"type":"text","value":" <"}]},{"type":"element","tag":"span","props":{"style":"--shiki-light:#174781;--shiki-default:#174781;--shiki-dark:#D2A6FF"},"children":[{"type":"text","value":" 0"}]},{"type":"element","tag":"span","props":{"style":"--shiki-light:#002339;--shiki-default:#002339;--shiki-dark:#BFBDB6"},"children":[{"type":"text","value":") {\n"}]}]},{"type":"element","tag":"span","props":{"class":"line","line":31},"children":[{"type":"element","tag":"span","props":{"style":"--shiki-light:#2F86D2;--shiki-default:#2F86D2;--shiki-dark:#BFBDB6"},"children":[{"type":"text","value":"        nextTime"}]},{"type":"element","tag":"span","props":{"style":"--shiki-light:#7B30D0;--shiki-default:#7B30D0;--shiki-dark:#F29668"},"children":[{"type":"text","value":" ="}]},{"type":"element","tag":"span","props":{"style":"--shiki-light:#174781;--shiki-default:#174781;--shiki-dark:#D2A6FF"},"children":[{"type":"text","value":" 0"}]},{"type":"element","tag":"span","props":{"style":"--shiki-light:#002339;--shiki-default:#002339;--shiki-dark:#BFBDB6B3"},"children":[{"type":"text","value":";\n"}]}]},{"type":"element","tag":"span","props":{"class":"line","line":32},"children":[{"type":"element","tag":"span","props":{"style":"--shiki-light:#002339;--shiki-default:#002339;--shiki-dark:#BFBDB6"},"children":[{"type":"text","value":"      }\n"}]}]},{"type":"element","tag":"span","props":{"class":"line","line":33},"children":[{"type":"element","tag":"span","props":{"style":"--shiki-light:#2F86D2;--shiki-default:#2F86D2;--shiki-dark:#BFBDB6"},"children":[{"type":"text","value":"      console"}]},{"type":"element","tag":"span","props":{"style":"--shiki-light:#002339;--shiki-default:#002339;--shiki-dark:#F29668"},"children":[{"type":"text","value":"."}]},{"type":"element","tag":"span","props":{"style":"--shiki-light:#7EB233;--shiki-default:#7EB233;--shiki-dark:#FFB454"},"children":[{"type":"text","value":"log"}]},{"type":"element","tag":"span","props":{"style":"--shiki-light:#002339;--shiki-default:#002339;--shiki-dark:#BFBDB6"},"children":[{"type":"text","value":"("}]},{"type":"element","tag":"span","props":{"style":"--shiki-light:#A44185;--shiki-default:#A44185;--shiki-dark:#AAD94C"},"children":[{"type":"text","value":"`执行下一次渲染的时间是："}]},{"type":"element","tag":"span","props":{"style":"--shiki-light:#A44185;--shiki-default:#A44185;--shiki-dark:#FF8F40"},"children":[{"type":"text","value":"${"}]},{"type":"element","tag":"span","props":{"style":"--shiki-light:#2F86D2;--shiki-default:#2F86D2;--shiki-dark:#BFBDB6"},"children":[{"type":"text","value":"nextTime"}]},{"type":"element","tag":"span","props":{"style":"--shiki-light:#A44185;--shiki-default:#A44185;--shiki-dark:#FF8F40"},"children":[{"type":"text","value":"}"}]},{"type":"element","tag":"span","props":{"style":"--shiki-light:#A44185;--shiki-default:#A44185;--shiki-dark:#AAD94C"},"children":[{"type":"text","value":"ms`"}]},{"type":"element","tag":"span","props":{"style":"--shiki-light:#002339;--shiki-default:#002339;--shiki-dark:#BFBDB6"},"children":[{"type":"text","value":")"}]},{"type":"element","tag":"span","props":{"style":"--shiki-light:#002339;--shiki-default:#002339;--shiki-dark:#BFBDB6B3"},"children":[{"type":"text","value":";\n"}]}]},{"type":"element","tag":"span","props":{"class":"line","line":34},"children":[{"type":"element","tag":"span","props":{"style":"--shiki-light:#7B30D0;--shiki-default:#7B30D0;--shiki-dark:#FF8F40"},"children":[{"type":"text","value":"      if"}]},{"type":"element","tag":"span","props":{"style":"--shiki-light:#002339;--shiki-default:#002339;--shiki-dark:#BFBDB6"},"children":[{"type":"text","value":" ("}]},{"type":"element","tag":"span","props":{"style":"--shiki-light:#2F86D2;--shiki-default:#2F86D2;--shiki-dark:#BFBDB6"},"children":[{"type":"text","value":"currentCount"}]},{"type":"element","tag":"span","props":{"style":"--shiki-light:#7B30D0;--shiki-default:#7B30D0;--shiki-dark:#F29668"},"children":[{"type":"text","value":" <="}]},{"type":"element","tag":"span","props":{"style":"--shiki-light:#174781;--shiki-default:#174781;--shiki-dark:#D2A6FF"},"children":[{"type":"text","value":" 0"}]},{"type":"element","tag":"span","props":{"style":"--shiki-light:#002339;--shiki-default:#002339;--shiki-dark:#BFBDB6"},"children":[{"type":"text","value":") {\n"}]}]},{"type":"element","tag":"span","props":{"class":"line","line":35},"children":[{"type":"element","tag":"span","props":{"style":"--shiki-light:#2F86D2;--shiki-default:#2F86D2;--shiki-dark:#BFBDB6"},"children":[{"type":"text","value":"        currentCount"}]},{"type":"element","tag":"span","props":{"style":"--shiki-light:#7B30D0;--shiki-default:#7B30D0;--shiki-dark:#F29668"},"children":[{"type":"text","value":" ="}]},{"type":"element","tag":"span","props":{"style":"--shiki-light:#174781;--shiki-default:#174781;--shiki-dark:#D2A6FF"},"children":[{"type":"text","value":" 0"}]},{"type":"element","tag":"span","props":{"style":"--shiki-light:#002339;--shiki-default:#002339;--shiki-dark:#BFBDB6B3"},"children":[{"type":"text","value":";\n"}]}]},{"type":"element","tag":"span","props":{"class":"line","line":36},"children":[{"type":"element","tag":"span","props":{"style":"--shiki-light:#7EB233;--shiki-default:#7EB233;--shiki-dark:#FFB454"},"children":[{"type":"text","value":"        cancelAnimationFrame"}]},{"type":"element","tag":"span","props":{"style":"--shiki-light:#002339;--shiki-default:#002339;--shiki-dark:#BFBDB6"},"children":[{"type":"text","value":"("}]},{"type":"element","tag":"span","props":{"style":"--shiki-light:#2F86D2;--shiki-default:#2F86D2;--shiki-dark:#BFBDB6"},"children":[{"type":"text","value":"requestRef"}]},{"type":"element","tag":"span","props":{"style":"--shiki-light:#002339;--shiki-default:#002339;--shiki-dark:#BFBDB6"},"children":[{"type":"text","value":")"}]},{"type":"element","tag":"span","props":{"style":"--shiki-light:#002339;--shiki-default:#002339;--shiki-dark:#BFBDB6B3"},"children":[{"type":"text","value":";\n"}]}]},{"type":"element","tag":"span","props":{"class":"line","line":37},"children":[{"type":"element","tag":"span","props":{"style":"--shiki-light:#2F86D2;--shiki-default:#2F86D2;--shiki-dark:#BFBDB6"},"children":[{"type":"text","value":"        console"}]},{"type":"element","tag":"span","props":{"style":"--shiki-light:#002339;--shiki-default:#002339;--shiki-dark:#F29668"},"children":[{"type":"text","value":"."}]},{"type":"element","tag":"span","props":{"style":"--shiki-light:#7EB233;--shiki-default:#7EB233;--shiki-dark:#FFB454"},"children":[{"type":"text","value":"log"}]},{"type":"element","tag":"span","props":{"style":"--shiki-light:#002339;--shiki-default:#002339;--shiki-dark:#BFBDB6"},"children":[{"type":"text","value":"("}]},{"type":"element","tag":"span","props":{"style":"--shiki-light:#A44185;--shiki-default:#A44185;--shiki-dark:#AAD94C"},"children":[{"type":"text","value":"`累计偏差值： "}]},{"type":"element","tag":"span","props":{"style":"--shiki-light:#A44185;--shiki-default:#A44185;--shiki-dark:#FF8F40"},"children":[{"type":"text","value":"${"}]},{"type":"element","tag":"span","props":{"style":"--shiki-light:#2F86D2;--shiki-default:#2F86D2;--shiki-dark:#BFBDB6"},"children":[{"type":"text","value":"endTime"}]},{"type":"element","tag":"span","props":{"style":"--shiki-light:#7B30D0;--shiki-default:#7B30D0;--shiki-dark:#F29668"},"children":[{"type":"text","value":" -"}]},{"type":"element","tag":"span","props":{"style":"--shiki-light:#2F86D2;--shiki-default:#2F86D2;--shiki-dark:#BFBDB6"},"children":[{"type":"text","value":" startTime"}]},{"type":"element","tag":"span","props":{"style":"--shiki-light:#7B30D0;--shiki-default:#7B30D0;--shiki-dark:#F29668"},"children":[{"type":"text","value":" -"}]},{"type":"element","tag":"span","props":{"style":"--shiki-light:#2F86D2;--shiki-default:#2F86D2;--shiki-dark:#BFBDB6"},"children":[{"type":"text","value":" totalDuration"}]},{"type":"element","tag":"span","props":{"style":"--shiki-light:#A44185;--shiki-default:#A44185;--shiki-dark:#FF8F40"},"children":[{"type":"text","value":"}"}]},{"type":"element","tag":"span","props":{"style":"--shiki-light:#A44185;--shiki-default:#A44185;--shiki-dark:#AAD94C"},"children":[{"type":"text","value":"ms`"}]},{"type":"element","tag":"span","props":{"style":"--shiki-light:#002339;--shiki-default:#002339;--shiki-dark:#BFBDB6"},"children":[{"type":"text","value":")"}]},{"type":"element","tag":"span","props":{"style":"--shiki-light:#002339;--shiki-default:#002339;--shiki-dark:#BFBDB6B3"},"children":[{"type":"text","value":";\n"}]}]},{"type":"element","tag":"span","props":{"class":"line","line":38},"children":[{"type":"element","tag":"span","props":{"style":"--shiki-light:#7B30D0;--shiki-default:#7B30D0;--shiki-dark:#FF8F40"},"children":[{"type":"text","value":"        return"}]},{"type":"element","tag":"span","props":{"style":"--shiki-light:#002339;--shiki-default:#002339;--shiki-dark:#BFBDB6B3"},"children":[{"type":"text","value":";\n"}]}]},{"type":"element","tag":"span","props":{"class":"line","line":39},"children":[{"type":"element","tag":"span","props":{"style":"--shiki-light:#002339;--shiki-default:#002339;--shiki-dark:#BFBDB6"},"children":[{"type":"text","value":"      }\n"}]}]},{"type":"element","tag":"span","props":{"class":"line","line":40},"children":[{"type":"element","tag":"span","props":{"style":"--shiki-light:#002339;--shiki-default:#002339;--shiki-dark:#BFBDB6"},"children":[{"type":"text","value":"    }\n"}]}]},{"type":"element","tag":"span","props":{"class":"line","line":41},"children":[{"type":"element","tag":"span","props":{"style":"--shiki-light:#002339;--shiki-default:#002339;--shiki-dark:#BFBDB6"},"children":[{"type":"text","value":"  } "}]},{"type":"element","tag":"span","props":{"style":"--shiki-light:#7B30D0;--shiki-default:#7B30D0;--shiki-dark:#FF8F40"},"children":[{"type":"text","value":"else"}]},{"type":"element","tag":"span","props":{"style":"--shiki-light:#002339;--shiki-default:#002339;--shiki-dark:#BFBDB6"},"children":[{"type":"text","value":" {\n"}]}]},{"type":"element","tag":"span","props":{"class":"line","line":42},"children":[{"type":"element","tag":"span","props":{"style":"--shiki-light:#2F86D2;--shiki-default:#2F86D2;--shiki-dark:#BFBDB6"},"children":[{"type":"text","value":"    startTime"}]},{"type":"element","tag":"span","props":{"style":"--shiki-light:#7B30D0;--shiki-default:#7B30D0;--shiki-dark:#F29668"},"children":[{"type":"text","value":" ="}]},{"type":"element","tag":"span","props":{"style":"--shiki-light:#7B30D0;--shiki-default:#7B30D0;--shiki-dark:#F29668"},"children":[{"type":"text","value":" new"}]},{"type":"element","tag":"span","props":{"style":"--shiki-light:#7EB233;--shiki-default:#7EB233;--shiki-dark:#FFB454"},"children":[{"type":"text","value":" Date"}]},{"type":"element","tag":"span","props":{"style":"--shiki-light:#002339;--shiki-default:#002339;--shiki-dark:#BFBDB6"},"children":[{"type":"text","value":"()"}]},{"type":"element","tag":"span","props":{"style":"--shiki-light:#002339;--shiki-default:#002339;--shiki-dark:#F29668"},"children":[{"type":"text","value":"."}]},{"type":"element","tag":"span","props":{"style":"--shiki-light:#7EB233;--shiki-default:#7EB233;--shiki-dark:#FFB454"},"children":[{"type":"text","value":"getTime"}]},{"type":"element","tag":"span","props":{"style":"--shiki-light:#002339;--shiki-default:#002339;--shiki-dark:#BFBDB6"},"children":[{"type":"text","value":"()"}]},{"type":"element","tag":"span","props":{"style":"--shiki-light:#002339;--shiki-default:#002339;--shiki-dark:#BFBDB6B3"},"children":[{"type":"text","value":";\n"}]}]},{"type":"element","tag":"span","props":{"class":"line","line":43},"children":[{"type":"element","tag":"span","props":{"style":"--shiki-light:#2F86D2;--shiki-default:#2F86D2;--shiki-dark:#BFBDB6"},"children":[{"type":"text","value":"    prevTime"}]},{"type":"element","tag":"span","props":{"style":"--shiki-light:#7B30D0;--shiki-default:#7B30D0;--shiki-dark:#F29668"},"children":[{"type":"text","value":" ="}]},{"type":"element","tag":"span","props":{"style":"--shiki-light:#2F86D2;--shiki-default:#2F86D2;--shiki-dark:#BFBDB6"},"children":[{"type":"text","value":" timestamp"}]},{"type":"element","tag":"span","props":{"style":"--shiki-light:#002339;--shiki-default:#002339;--shiki-dark:#BFBDB6B3"},"children":[{"type":"text","value":";\n"}]}]},{"type":"element","tag":"span","props":{"class":"line","line":44},"children":[{"type":"element","tag":"span","props":{"style":"--shiki-light:#2F86D2;--shiki-default:#2F86D2;--shiki-dark:#BFBDB6"},"children":[{"type":"text","value":"    endTime"}]},{"type":"element","tag":"span","props":{"style":"--shiki-light:#7B30D0;--shiki-default:#7B30D0;--shiki-dark:#F29668"},"children":[{"type":"text","value":" ="}]},{"type":"element","tag":"span","props":{"style":"--shiki-light:#7B30D0;--shiki-default:#7B30D0;--shiki-dark:#F29668"},"children":[{"type":"text","value":" new"}]},{"type":"element","tag":"span","props":{"style":"--shiki-light:#7EB233;--shiki-default:#7EB233;--shiki-dark:#FFB454"},"children":[{"type":"text","value":" Date"}]},{"type":"element","tag":"span","props":{"style":"--shiki-light:#002339;--shiki-default:#002339;--shiki-dark:#BFBDB6"},"children":[{"type":"text","value":"()"}]},{"type":"element","tag":"span","props":{"style":"--shiki-light:#002339;--shiki-default:#002339;--shiki-dark:#F29668"},"children":[{"type":"text","value":"."}]},{"type":"element","tag":"span","props":{"style":"--shiki-light:#7EB233;--shiki-default:#7EB233;--shiki-dark:#FFB454"},"children":[{"type":"text","value":"getTime"}]},{"type":"element","tag":"span","props":{"style":"--shiki-light:#002339;--shiki-default:#002339;--shiki-dark:#BFBDB6"},"children":[{"type":"text","value":"()"}]},{"type":"element","tag":"span","props":{"style":"--shiki-light:#002339;--shiki-default:#002339;--shiki-dark:#BFBDB6B3"},"children":[{"type":"text","value":";\n"}]}]},{"type":"element","tag":"span","props":{"class":"line","line":45},"children":[{"type":"element","tag":"span","props":{"style":"--shiki-light:#002339;--shiki-default:#002339;--shiki-dark:#BFBDB6"},"children":[{"type":"text","value":"  }\n"}]}]},{"type":"element","tag":"span","props":{"class":"line","line":46},"children":[{"type":"element","tag":"span","props":{"style":"--shiki-light:#2F86D2;--shiki-default:#2F86D2;--shiki-dark:#BFBDB6"},"children":[{"type":"text","value":"  requestRef"}]},{"type":"element","tag":"span","props":{"style":"--shiki-light:#7B30D0;--shiki-default:#7B30D0;--shiki-dark:#F29668"},"children":[{"type":"text","value":" ="}]},{"type":"element","tag":"span","props":{"style":"--shiki-light:#7EB233;--shiki-default:#7EB233;--shiki-dark:#FFB454"},"children":[{"type":"text","value":" requestAnimationFrame"}]},{"type":"element","tag":"span","props":{"style":"--shiki-light:#002339;--shiki-default:#002339;--shiki-dark:#BFBDB6"},"children":[{"type":"text","value":"("}]},{"type":"element","tag":"span","props":{"style":"--shiki-light:#2F86D2;--shiki-default:#2F86D2;--shiki-dark:#BFBDB6"},"children":[{"type":"text","value":"animate"}]},{"type":"element","tag":"span","props":{"style":"--shiki-light:#002339;--shiki-default:#002339;--shiki-dark:#BFBDB6"},"children":[{"type":"text","value":")"}]},{"type":"element","tag":"span","props":{"style":"--shiki-light:#002339;--shiki-default:#002339;--shiki-dark:#BFBDB6B3"},"children":[{"type":"text","value":";\n"}]}]},{"type":"element","tag":"span","props":{"class":"line","line":47},"children":[{"type":"element","tag":"span","props":{"style":"--shiki-light:#002339;--shiki-default:#002339;--shiki-dark:#BFBDB6"},"children":[{"type":"text","value":"}"}]},{"type":"element","tag":"span","props":{"style":"--shiki-light:#002339;--shiki-default:#002339;--shiki-dark:#BFBDB6B3"},"children":[{"type":"text","value":";\n"}]}]},{"type":"element","tag":"span","props":{"class":"line","line":48},"children":[{"type":"element","tag":"span","props":{"emptyLinePlaceholder":true},"children":[{"type":"text","value":"\n"}]}]},{"type":"element","tag":"span","props":{"class":"line","line":49},"children":[{"type":"element","tag":"span","props":{"style":"--shiki-light:#2F86D2;--shiki-default:#2F86D2;--shiki-dark:#BFBDB6"},"children":[{"type":"text","value":"requestRef"}]},{"type":"element","tag":"span","props":{"style":"--shiki-light:#7B30D0;--shiki-default:#7B30D0;--shiki-dark:#F29668"},"children":[{"type":"text","value":" ="}]},{"type":"element","tag":"span","props":{"style":"--shiki-light:#7EB233;--shiki-default:#7EB233;--shiki-dark:#FFB454"},"children":[{"type":"text","value":" requestAnimationFrame"}]},{"type":"element","tag":"span","props":{"style":"--shiki-light:#002339;--shiki-default:#002339;--shiki-dark:#BFBDB6"},"children":[{"type":"text","value":"("}]},{"type":"element","tag":"span","props":{"style":"--shiki-light:#2F86D2;--shiki-default:#2F86D2;--shiki-dark:#BFBDB6"},"children":[{"type":"text","value":"animate"}]},{"type":"element","tag":"span","props":{"style":"--shiki-light:#002339;--shiki-default:#002339;--shiki-dark:#BFBDB6"},"children":[{"type":"text","value":")"}]},{"type":"element","tag":"span","props":{"style":"--shiki-light:#002339;--shiki-default:#002339;--shiki-dark:#BFBDB6B3"},"children":[{"type":"text","value":";\n"}]}]}]}]},{"type":"element","tag":"style","props":{},"children":[{"type":"text","value":"html .light .shiki span {color: var(--shiki-light);background: var(--shiki-light-bg);font-style: var(--shiki-light-font-style);font-weight: var(--shiki-light-font-weight);text-decoration: var(--shiki-light-text-decoration);}html.light .shiki span {color: var(--shiki-light);background: var(--shiki-light-bg);font-style: var(--shiki-light-font-style);font-weight: var(--shiki-light-font-weight);text-decoration: var(--shiki-light-text-decoration);}html .default .shiki span {color: var(--shiki-default);background: var(--shiki-default-bg);font-style: var(--shiki-default-font-style);font-weight: var(--shiki-default-font-weight);text-decoration: var(--shiki-default-text-decoration);}html .shiki span {color: var(--shiki-default);background: var(--shiki-default-bg);font-style: var(--shiki-default-font-style);font-weight: var(--shiki-default-font-weight);text-decoration: var(--shiki-default-text-decoration);}html .dark .shiki span {color: var(--shiki-dark);background: var(--shiki-dark-bg);font-style: var(--shiki-dark-font-style);font-weight: var(--shiki-dark-font-weight);text-decoration: var(--shiki-dark-text-decoration);}html.dark .shiki span {color: var(--shiki-dark);background: var(--shiki-dark-bg);font-style: var(--shiki-dark-font-style);font-weight: var(--shiki-dark-font-weight);text-decoration: var(--shiki-dark-text-decoration);}"}]}],"toc":{"title":"","searchDepth":5,"depth":5,"links":[]}},"_type":"markdown","_id":"content:3.frontend-code-assessment:2.scene:countdown.md","_source":"content","_file":"3.frontend-code-assessment/2.scene/countdown.md","_extension":"md"}