{"_path":"/algorithm/leetcode/major/kids-with-the-greatest-number-of-candies","_dir":"major","_draft":false,"_partial":false,"_locale":"","title":"No.1431 拥有最多糖果的孩子","description":"给你一个数组 candies 和一个整数 extraCandies ，其中 candies[i] 代表第 i 个孩子拥有的糖果数目。","url":"https://leetcode.cn/problems/kids-with-the-greatest-number-of-candies","body":{"type":"root","children":[{"type":"element","tag":"p","props":{},"children":[{"type":"text","value":"给你一个数组 candies 和一个整数 extraCandies ，其中 candies[i] 代表第 i 个孩子拥有的糖果数目。"}]},{"type":"element","tag":"p","props":{},"children":[{"type":"text","value":"对每一个孩子，检查是否存在一种方案，将额外的 extraCandies 个糖果分配给孩子们之后，此孩子有 最多 的糖果。注意，允许有多个孩子同时拥有 最多 的糖果数目。"}]},{"type":"element","tag":"p","props":{},"children":[{"type":"text","value":"示例 1："}]},{"type":"element","tag":"pre","props":{"className":"language-text shiki shiki-themes vitesse-light vitesse-light vitesse-dark","code":"输入：candies = [2,3,5,1,3], extraCandies = 3\n输出：[true,true,true,false,true]\n解释：\n孩子 1 有 2 个糖果，如果他得到所有额外的糖果（3 个），那么他总共有 5 个糖果，他将成为拥有最多糖果的孩子。\n孩子 2 有 3 个糖果，如果他得到至少 2 个额外糖果，那么他将成为拥有最多糖果的孩子。\n孩子 3 有 5 个糖果，他已经是拥有最多糖果的孩子。\n孩子 4 有 1 个糖果，即使他得到所有额外的糖果，他也只有 4 个糖果，无法成为拥有糖果最多的孩子。\n孩子 5 有 3 个糖果，如果他得到至少 2 个额外糖果，那么他将成为拥有最多糖果的孩子。\n","language":"text","meta":"","style":""},"children":[{"type":"element","tag":"code","props":{"__ignoreMap":""},"children":[{"type":"element","tag":"span","props":{"class":"line","line":1},"children":[{"type":"element","tag":"span","props":{},"children":[{"type":"text","value":"输入：candies = [2,3,5,1,3], extraCandies = 3\n"}]}]},{"type":"element","tag":"span","props":{"class":"line","line":2},"children":[{"type":"element","tag":"span","props":{},"children":[{"type":"text","value":"输出：[true,true,true,false,true]\n"}]}]},{"type":"element","tag":"span","props":{"class":"line","line":3},"children":[{"type":"element","tag":"span","props":{},"children":[{"type":"text","value":"解释：\n"}]}]},{"type":"element","tag":"span","props":{"class":"line","line":4},"children":[{"type":"element","tag":"span","props":{},"children":[{"type":"text","value":"孩子 1 有 2 个糖果，如果他得到所有额外的糖果（3 个），那么他总共有 5 个糖果，他将成为拥有最多糖果的孩子。\n"}]}]},{"type":"element","tag":"span","props":{"class":"line","line":5},"children":[{"type":"element","tag":"span","props":{},"children":[{"type":"text","value":"孩子 2 有 3 个糖果，如果他得到至少 2 个额外糖果，那么他将成为拥有最多糖果的孩子。\n"}]}]},{"type":"element","tag":"span","props":{"class":"line","line":6},"children":[{"type":"element","tag":"span","props":{},"children":[{"type":"text","value":"孩子 3 有 5 个糖果，他已经是拥有最多糖果的孩子。\n"}]}]},{"type":"element","tag":"span","props":{"class":"line","line":7},"children":[{"type":"element","tag":"span","props":{},"children":[{"type":"text","value":"孩子 4 有 1 个糖果，即使他得到所有额外的糖果，他也只有 4 个糖果，无法成为拥有糖果最多的孩子。\n"}]}]},{"type":"element","tag":"span","props":{"class":"line","line":8},"children":[{"type":"element","tag":"span","props":{},"children":[{"type":"text","value":"孩子 5 有 3 个糖果，如果他得到至少 2 个额外糖果，那么他将成为拥有最多糖果的孩子。\n"}]}]}]}]},{"type":"element","tag":"p","props":{},"children":[{"type":"text","value":"示例 2："}]},{"type":"element","tag":"pre","props":{"className":"language-text shiki shiki-themes vitesse-light vitesse-light vitesse-dark","code":"输入：candies = [4,2,1,1,2], extraCandies = 1\n输出：[true,false,false,false,false]\n解释：只有 1 个额外糖果，所以不管额外糖果给谁，只有孩子 1 可以成为拥有糖果最多的孩子。\n","language":"text","meta":"","style":""},"children":[{"type":"element","tag":"code","props":{"__ignoreMap":""},"children":[{"type":"element","tag":"span","props":{"class":"line","line":1},"children":[{"type":"element","tag":"span","props":{},"children":[{"type":"text","value":"输入：candies = [4,2,1,1,2], extraCandies = 1\n"}]}]},{"type":"element","tag":"span","props":{"class":"line","line":2},"children":[{"type":"element","tag":"span","props":{},"children":[{"type":"text","value":"输出：[true,false,false,false,false]\n"}]}]},{"type":"element","tag":"span","props":{"class":"line","line":3},"children":[{"type":"element","tag":"span","props":{},"children":[{"type":"text","value":"解释：只有 1 个额外糖果，所以不管额外糖果给谁，只有孩子 1 可以成为拥有糖果最多的孩子。\n"}]}]}]}]},{"type":"element","tag":"p","props":{},"children":[{"type":"text","value":"示例 3："}]},{"type":"element","tag":"pre","props":{"className":"language-text shiki shiki-themes vitesse-light vitesse-light vitesse-dark","code":"输入：candies = [12,1,12], extraCandies = 10\n输出：[true,false,true]\n","language":"text","meta":"","style":""},"children":[{"type":"element","tag":"code","props":{"__ignoreMap":""},"children":[{"type":"element","tag":"span","props":{"class":"line","line":1},"children":[{"type":"element","tag":"span","props":{},"children":[{"type":"text","value":"输入：candies = [12,1,12], extraCandies = 10\n"}]}]},{"type":"element","tag":"span","props":{"class":"line","line":2},"children":[{"type":"element","tag":"span","props":{},"children":[{"type":"text","value":"输出：[true,false,true]\n"}]}]}]}]},{"type":"element","tag":"p","props":{},"children":[{"type":"text","value":"提示："}]},{"type":"element","tag":"ul","props":{},"children":[{"type":"element","tag":"li","props":{},"children":[{"type":"text","value":"2 <= candies.length <= 100"}]},{"type":"element","tag":"li","props":{},"children":[{"type":"text","value":"1 <= candies[i] <= 100"}]},{"type":"element","tag":"li","props":{},"children":[{"type":"text","value":"1 <= extraCandies <= 50"}]}]},{"type":"element","tag":"h2","props":{"id":"解题思路"},"children":[{"type":"text","value":"解题思路"}]},{"type":"element","tag":"h2","props":{"id":"实现"},"children":[{"type":"text","value":"实现"}]},{"type":"element","tag":"pre","props":{"className":"language-js shiki shiki-themes vitesse-light vitesse-light vitesse-dark","code":"/**\n * @param {number[]} candies\n * @param {number} extraCandies\n * @return {boolean[]}\n */\nvar kidsWithCandies = function (candies, extraCandies) {\n  const max = Math.max.apply([], candies);\n  let res = [];\n  for (let i = 0; i < candies.length; i++) {\n    let currentMax = candies[i] + extraCandies;\n    res[i] = currentMax >= max;\n  }\n  return res;\n};\n","language":"js","meta":"","style":""},"children":[{"type":"element","tag":"code","props":{"__ignoreMap":""},"children":[{"type":"element","tag":"span","props":{"class":"line","line":1},"children":[{"type":"element","tag":"span","props":{"style":"--shiki-light:#A0ADA0;--shiki-default:#A0ADA0;--shiki-dark:#758575DD"},"children":[{"type":"text","value":"/**\n"}]}]},{"type":"element","tag":"span","props":{"class":"line","line":2},"children":[{"type":"element","tag":"span","props":{"style":"--shiki-light:#A0ADA0;--shiki-default:#A0ADA0;--shiki-dark:#758575DD"},"children":[{"type":"text","value":" * "}]},{"type":"element","tag":"span","props":{"style":"--shiki-light:#999999;--shiki-default:#999999;--shiki-dark:#666666"},"children":[{"type":"text","value":"@"}]},{"type":"element","tag":"span","props":{"style":"--shiki-light:#1E754F;--shiki-default:#1E754F;--shiki-dark:#4D9375"},"children":[{"type":"text","value":"param"}]},{"type":"element","tag":"span","props":{"style":"--shiki-light:#999999;--shiki-default:#999999;--shiki-dark:#666666"},"children":[{"type":"text","value":" {"}]},{"type":"element","tag":"span","props":{"style":"--shiki-light:#2E8F82;--shiki-default:#2E8F82;--shiki-dark:#5DA994"},"children":[{"type":"text","value":"number[]"}]},{"type":"element","tag":"span","props":{"style":"--shiki-light:#999999;--shiki-default:#999999;--shiki-dark:#666666"},"children":[{"type":"text","value":"}"}]},{"type":"element","tag":"span","props":{"style":"--shiki-light:#B07D48;--shiki-default:#B07D48;--shiki-dark:#BD976A"},"children":[{"type":"text","value":" candies\n"}]}]},{"type":"element","tag":"span","props":{"class":"line","line":3},"children":[{"type":"element","tag":"span","props":{"style":"--shiki-light:#A0ADA0;--shiki-default:#A0ADA0;--shiki-dark:#758575DD"},"children":[{"type":"text","value":" * "}]},{"type":"element","tag":"span","props":{"style":"--shiki-light:#999999;--shiki-default:#999999;--shiki-dark:#666666"},"children":[{"type":"text","value":"@"}]},{"type":"element","tag":"span","props":{"style":"--shiki-light:#1E754F;--shiki-default:#1E754F;--shiki-dark:#4D9375"},"children":[{"type":"text","value":"param"}]},{"type":"element","tag":"span","props":{"style":"--shiki-light:#999999;--shiki-default:#999999;--shiki-dark:#666666"},"children":[{"type":"text","value":" {"}]},{"type":"element","tag":"span","props":{"style":"--shiki-light:#2E8F82;--shiki-default:#2E8F82;--shiki-dark:#5DA994"},"children":[{"type":"text","value":"number"}]},{"type":"element","tag":"span","props":{"style":"--shiki-light:#999999;--shiki-default:#999999;--shiki-dark:#666666"},"children":[{"type":"text","value":"}"}]},{"type":"element","tag":"span","props":{"style":"--shiki-light:#B07D48;--shiki-default:#B07D48;--shiki-dark:#BD976A"},"children":[{"type":"text","value":" extraCandies\n"}]}]},{"type":"element","tag":"span","props":{"class":"line","line":4},"children":[{"type":"element","tag":"span","props":{"style":"--shiki-light:#A0ADA0;--shiki-default:#A0ADA0;--shiki-dark:#758575DD"},"children":[{"type":"text","value":" * "}]},{"type":"element","tag":"span","props":{"style":"--shiki-light:#999999;--shiki-default:#999999;--shiki-dark:#666666"},"children":[{"type":"text","value":"@"}]},{"type":"element","tag":"span","props":{"style":"--shiki-light:#1E754F;--shiki-default:#1E754F;--shiki-dark:#4D9375"},"children":[{"type":"text","value":"return"}]},{"type":"element","tag":"span","props":{"style":"--shiki-light:#999999;--shiki-default:#999999;--shiki-dark:#666666"},"children":[{"type":"text","value":" {"}]},{"type":"element","tag":"span","props":{"style":"--shiki-light:#2E8F82;--shiki-default:#2E8F82;--shiki-dark:#5DA994"},"children":[{"type":"text","value":"boolean[]"}]},{"type":"element","tag":"span","props":{"style":"--shiki-light:#999999;--shiki-default:#999999;--shiki-dark:#666666"},"children":[{"type":"text","value":"}\n"}]}]},{"type":"element","tag":"span","props":{"class":"line","line":5},"children":[{"type":"element","tag":"span","props":{"style":"--shiki-light:#A0ADA0;--shiki-default:#A0ADA0;--shiki-dark:#758575DD"},"children":[{"type":"text","value":" */\n"}]}]},{"type":"element","tag":"span","props":{"class":"line","line":6},"children":[{"type":"element","tag":"span","props":{"style":"--shiki-light:#AB5959;--shiki-default:#AB5959;--shiki-dark:#CB7676"},"children":[{"type":"text","value":"var"}]},{"type":"element","tag":"span","props":{"style":"--shiki-light:#59873A;--shiki-default:#59873A;--shiki-dark:#80A665"},"children":[{"type":"text","value":" kidsWithCandies"}]},{"type":"element","tag":"span","props":{"style":"--shiki-light:#999999;--shiki-default:#999999;--shiki-dark:#666666"},"children":[{"type":"text","value":" ="}]},{"type":"element","tag":"span","props":{"style":"--shiki-light:#AB5959;--shiki-default:#AB5959;--shiki-dark:#CB7676"},"children":[{"type":"text","value":" function"}]},{"type":"element","tag":"span","props":{"style":"--shiki-light:#999999;--shiki-default:#999999;--shiki-dark:#666666"},"children":[{"type":"text","value":" ("}]},{"type":"element","tag":"span","props":{"style":"--shiki-light:#B07D48;--shiki-default:#B07D48;--shiki-dark:#BD976A"},"children":[{"type":"text","value":"candies"}]},{"type":"element","tag":"span","props":{"style":"--shiki-light:#999999;--shiki-default:#999999;--shiki-dark:#666666"},"children":[{"type":"text","value":","}]},{"type":"element","tag":"span","props":{"style":"--shiki-light:#B07D48;--shiki-default:#B07D48;--shiki-dark:#BD976A"},"children":[{"type":"text","value":" extraCandies"}]},{"type":"element","tag":"span","props":{"style":"--shiki-light:#999999;--shiki-default:#999999;--shiki-dark:#666666"},"children":[{"type":"text","value":")"}]},{"type":"element","tag":"span","props":{"style":"--shiki-light:#999999;--shiki-default:#999999;--shiki-dark:#666666"},"children":[{"type":"text","value":" {\n"}]}]},{"type":"element","tag":"span","props":{"class":"line","line":7},"children":[{"type":"element","tag":"span","props":{"style":"--shiki-light:#AB5959;--shiki-default:#AB5959;--shiki-dark:#CB7676"},"children":[{"type":"text","value":"  const"}]},{"type":"element","tag":"span","props":{"style":"--shiki-light:#B07D48;--shiki-default:#B07D48;--shiki-dark:#BD976A"},"children":[{"type":"text","value":" max"}]},{"type":"element","tag":"span","props":{"style":"--shiki-light:#999999;--shiki-default:#999999;--shiki-dark:#666666"},"children":[{"type":"text","value":" ="}]},{"type":"element","tag":"span","props":{"style":"--shiki-light:#B07D48;--shiki-default:#B07D48;--shiki-dark:#BD976A"},"children":[{"type":"text","value":" Math"}]},{"type":"element","tag":"span","props":{"style":"--shiki-light:#999999;--shiki-default:#999999;--shiki-dark:#666666"},"children":[{"type":"text","value":"."}]},{"type":"element","tag":"span","props":{"style":"--shiki-light:#B07D48;--shiki-default:#B07D48;--shiki-dark:#BD976A"},"children":[{"type":"text","value":"max"}]},{"type":"element","tag":"span","props":{"style":"--shiki-light:#999999;--shiki-default:#999999;--shiki-dark:#666666"},"children":[{"type":"text","value":"."}]},{"type":"element","tag":"span","props":{"style":"--shiki-light:#59873A;--shiki-default:#59873A;--shiki-dark:#80A665"},"children":[{"type":"text","value":"apply"}]},{"type":"element","tag":"span","props":{"style":"--shiki-light:#999999;--shiki-default:#999999;--shiki-dark:#666666"},"children":[{"type":"text","value":"([],"}]},{"type":"element","tag":"span","props":{"style":"--shiki-light:#B07D48;--shiki-default:#B07D48;--shiki-dark:#BD976A"},"children":[{"type":"text","value":" candies"}]},{"type":"element","tag":"span","props":{"style":"--shiki-light:#999999;--shiki-default:#999999;--shiki-dark:#666666"},"children":[{"type":"text","value":");\n"}]}]},{"type":"element","tag":"span","props":{"class":"line","line":8},"children":[{"type":"element","tag":"span","props":{"style":"--shiki-light:#AB5959;--shiki-default:#AB5959;--shiki-dark:#CB7676"},"children":[{"type":"text","value":"  let"}]},{"type":"element","tag":"span","props":{"style":"--shiki-light:#B07D48;--shiki-default:#B07D48;--shiki-dark:#BD976A"},"children":[{"type":"text","value":" res"}]},{"type":"element","tag":"span","props":{"style":"--shiki-light:#999999;--shiki-default:#999999;--shiki-dark:#666666"},"children":[{"type":"text","value":" ="}]},{"type":"element","tag":"span","props":{"style":"--shiki-light:#999999;--shiki-default:#999999;--shiki-dark:#666666"},"children":[{"type":"text","value":" [];\n"}]}]},{"type":"element","tag":"span","props":{"class":"line","line":9},"children":[{"type":"element","tag":"span","props":{"style":"--shiki-light:#1E754F;--shiki-default:#1E754F;--shiki-dark:#4D9375"},"children":[{"type":"text","value":"  for"}]},{"type":"element","tag":"span","props":{"style":"--shiki-light:#999999;--shiki-default:#999999;--shiki-dark:#666666"},"children":[{"type":"text","value":" ("}]},{"type":"element","tag":"span","props":{"style":"--shiki-light:#AB5959;--shiki-default:#AB5959;--shiki-dark:#CB7676"},"children":[{"type":"text","value":"let"}]},{"type":"element","tag":"span","props":{"style":"--shiki-light:#B07D48;--shiki-default:#B07D48;--shiki-dark:#BD976A"},"children":[{"type":"text","value":" i"}]},{"type":"element","tag":"span","props":{"style":"--shiki-light:#999999;--shiki-default:#999999;--shiki-dark:#666666"},"children":[{"type":"text","value":" ="}]},{"type":"element","tag":"span","props":{"style":"--shiki-light:#2F798A;--shiki-default:#2F798A;--shiki-dark:#4C9A91"},"children":[{"type":"text","value":" 0"}]},{"type":"element","tag":"span","props":{"style":"--shiki-light:#999999;--shiki-default:#999999;--shiki-dark:#666666"},"children":[{"type":"text","value":";"}]},{"type":"element","tag":"span","props":{"style":"--shiki-light:#B07D48;--shiki-default:#B07D48;--shiki-dark:#BD976A"},"children":[{"type":"text","value":" i"}]},{"type":"element","tag":"span","props":{"style":"--shiki-light:#999999;--shiki-default:#999999;--shiki-dark:#666666"},"children":[{"type":"text","value":" <"}]},{"type":"element","tag":"span","props":{"style":"--shiki-light:#B07D48;--shiki-default:#B07D48;--shiki-dark:#BD976A"},"children":[{"type":"text","value":" candies"}]},{"type":"element","tag":"span","props":{"style":"--shiki-light:#999999;--shiki-default:#999999;--shiki-dark:#666666"},"children":[{"type":"text","value":"."}]},{"type":"element","tag":"span","props":{"style":"--shiki-light:#998418;--shiki-default:#998418;--shiki-dark:#B8A965"},"children":[{"type":"text","value":"length"}]},{"type":"element","tag":"span","props":{"style":"--shiki-light:#999999;--shiki-default:#999999;--shiki-dark:#666666"},"children":[{"type":"text","value":";"}]},{"type":"element","tag":"span","props":{"style":"--shiki-light:#B07D48;--shiki-default:#B07D48;--shiki-dark:#BD976A"},"children":[{"type":"text","value":" i"}]},{"type":"element","tag":"span","props":{"style":"--shiki-light:#AB5959;--shiki-default:#AB5959;--shiki-dark:#CB7676"},"children":[{"type":"text","value":"++"}]},{"type":"element","tag":"span","props":{"style":"--shiki-light:#999999;--shiki-default:#999999;--shiki-dark:#666666"},"children":[{"type":"text","value":")"}]},{"type":"element","tag":"span","props":{"style":"--shiki-light:#999999;--shiki-default:#999999;--shiki-dark:#666666"},"children":[{"type":"text","value":" {\n"}]}]},{"type":"element","tag":"span","props":{"class":"line","line":10},"children":[{"type":"element","tag":"span","props":{"style":"--shiki-light:#AB5959;--shiki-default:#AB5959;--shiki-dark:#CB7676"},"children":[{"type":"text","value":"    let"}]},{"type":"element","tag":"span","props":{"style":"--shiki-light:#B07D48;--shiki-default:#B07D48;--shiki-dark:#BD976A"},"children":[{"type":"text","value":" currentMax"}]},{"type":"element","tag":"span","props":{"style":"--shiki-light:#999999;--shiki-default:#999999;--shiki-dark:#666666"},"children":[{"type":"text","value":" ="}]},{"type":"element","tag":"span","props":{"style":"--shiki-light:#B07D48;--shiki-default:#B07D48;--shiki-dark:#BD976A"},"children":[{"type":"text","value":" candies"}]},{"type":"element","tag":"span","props":{"style":"--shiki-light:#999999;--shiki-default:#999999;--shiki-dark:#666666"},"children":[{"type":"text","value":"["}]},{"type":"element","tag":"span","props":{"style":"--shiki-light:#B07D48;--shiki-default:#B07D48;--shiki-dark:#BD976A"},"children":[{"type":"text","value":"i"}]},{"type":"element","tag":"span","props":{"style":"--shiki-light:#999999;--shiki-default:#999999;--shiki-dark:#666666"},"children":[{"type":"text","value":"]"}]},{"type":"element","tag":"span","props":{"style":"--shiki-light:#AB5959;--shiki-default:#AB5959;--shiki-dark:#CB7676"},"children":[{"type":"text","value":" +"}]},{"type":"element","tag":"span","props":{"style":"--shiki-light:#B07D48;--shiki-default:#B07D48;--shiki-dark:#BD976A"},"children":[{"type":"text","value":" extraCandies"}]},{"type":"element","tag":"span","props":{"style":"--shiki-light:#999999;--shiki-default:#999999;--shiki-dark:#666666"},"children":[{"type":"text","value":";\n"}]}]},{"type":"element","tag":"span","props":{"class":"line","line":11},"children":[{"type":"element","tag":"span","props":{"style":"--shiki-light:#B07D48;--shiki-default:#B07D48;--shiki-dark:#BD976A"},"children":[{"type":"text","value":"    res"}]},{"type":"element","tag":"span","props":{"style":"--shiki-light:#999999;--shiki-default:#999999;--shiki-dark:#666666"},"children":[{"type":"text","value":"["}]},{"type":"element","tag":"span","props":{"style":"--shiki-light:#B07D48;--shiki-default:#B07D48;--shiki-dark:#BD976A"},"children":[{"type":"text","value":"i"}]},{"type":"element","tag":"span","props":{"style":"--shiki-light:#999999;--shiki-default:#999999;--shiki-dark:#666666"},"children":[{"type":"text","value":"]"}]},{"type":"element","tag":"span","props":{"style":"--shiki-light:#999999;--shiki-default:#999999;--shiki-dark:#666666"},"children":[{"type":"text","value":" ="}]},{"type":"element","tag":"span","props":{"style":"--shiki-light:#B07D48;--shiki-default:#B07D48;--shiki-dark:#BD976A"},"children":[{"type":"text","value":" currentMax"}]},{"type":"element","tag":"span","props":{"style":"--shiki-light:#999999;--shiki-default:#999999;--shiki-dark:#666666"},"children":[{"type":"text","value":" >="}]},{"type":"element","tag":"span","props":{"style":"--shiki-light:#B07D48;--shiki-default:#B07D48;--shiki-dark:#BD976A"},"children":[{"type":"text","value":" max"}]},{"type":"element","tag":"span","props":{"style":"--shiki-light:#999999;--shiki-default:#999999;--shiki-dark:#666666"},"children":[{"type":"text","value":";\n"}]}]},{"type":"element","tag":"span","props":{"class":"line","line":12},"children":[{"type":"element","tag":"span","props":{"style":"--shiki-light:#999999;--shiki-default:#999999;--shiki-dark:#666666"},"children":[{"type":"text","value":"  }\n"}]}]},{"type":"element","tag":"span","props":{"class":"line","line":13},"children":[{"type":"element","tag":"span","props":{"style":"--shiki-light:#1E754F;--shiki-default:#1E754F;--shiki-dark:#4D9375"},"children":[{"type":"text","value":"  return"}]},{"type":"element","tag":"span","props":{"style":"--shiki-light:#B07D48;--shiki-default:#B07D48;--shiki-dark:#BD976A"},"children":[{"type":"text","value":" res"}]},{"type":"element","tag":"span","props":{"style":"--shiki-light:#999999;--shiki-default:#999999;--shiki-dark:#666666"},"children":[{"type":"text","value":";\n"}]}]},{"type":"element","tag":"span","props":{"class":"line","line":14},"children":[{"type":"element","tag":"span","props":{"style":"--shiki-light:#999999;--shiki-default:#999999;--shiki-dark:#666666"},"children":[{"type":"text","value":"};\n"}]}]}]}]},{"type":"element","tag":"style","props":{},"children":[{"type":"text","value":"html .light .shiki span {color: var(--shiki-light);background: var(--shiki-light-bg);font-style: var(--shiki-light-font-style);font-weight: var(--shiki-light-font-weight);text-decoration: var(--shiki-light-text-decoration);}html.light .shiki span {color: var(--shiki-light);background: var(--shiki-light-bg);font-style: var(--shiki-light-font-style);font-weight: var(--shiki-light-font-weight);text-decoration: var(--shiki-light-text-decoration);}html .default .shiki span {color: var(--shiki-default);background: var(--shiki-default-bg);font-style: var(--shiki-default-font-style);font-weight: var(--shiki-default-font-weight);text-decoration: var(--shiki-default-text-decoration);}html .shiki span {color: var(--shiki-default);background: var(--shiki-default-bg);font-style: var(--shiki-default-font-style);font-weight: var(--shiki-default-font-weight);text-decoration: var(--shiki-default-text-decoration);}html .dark .shiki span {color: var(--shiki-dark);background: var(--shiki-dark-bg);font-style: var(--shiki-dark-font-style);font-weight: var(--shiki-dark-font-weight);text-decoration: var(--shiki-dark-text-decoration);}html.dark .shiki span {color: var(--shiki-dark);background: var(--shiki-dark-bg);font-style: var(--shiki-dark-font-style);font-weight: var(--shiki-dark-font-weight);text-decoration: var(--shiki-dark-text-decoration);}"}]}],"toc":{"title":"","searchDepth":5,"depth":5,"links":[{"id":"解题思路","depth":2,"text":"解题思路"},{"id":"实现","depth":2,"text":"实现"}]}},"_type":"markdown","_id":"content:1.algorithm:3.leetcode:3.major:1431.kids-with-the-greatest-number-of-candies.md","_source":"content","_file":"1.algorithm/3.leetcode/3.major/1431.kids-with-the-greatest-number-of-candies.md","_extension":"md"}