{"_path":"/frontend-code-assessment/scene/most-frequent-characters-in-content","_dir":"scene","_draft":false,"_partial":false,"_locale":"","title":"内容中出现频率最高的字符","description":"","body":{"type":"root","children":[{"type":"element","tag":"pre","props":{"className":"language-js shiki shiki-themes slack-ochin slack-ochin ayu-dark","code":"function findMostWord(content) {\n  // 合法性判断\n  if (!content) return;\n\n  // 参数处理\n  content = content.trim().toLowerCase();\n\n  let wordList = content.match(/[a-z]+/g);\n  let visited = [];\n  let maxNum = 0;\n  let maxWord = \"\";\n\n  content = \" \" + wordList.join(\"  \") + \" \";\n\n  // 遍历判断单词出现次数\n  wordList.forEach(function (item) {\n    if (visited.indexOf(item) < 0) {\n      // 加入 visited\n      visited.push(item);\n\n      let word = new RegExp(\" \" + item + \" \", \"g\");\n      let num = content.match(word).length;\n\n      if (num > maxNum) {\n        maxNum = num;\n        maxWord = item;\n      }\n    }\n  });\n\n  return maxWord + \"  \" + maxNum;\n}\n","language":"js","meta":"","style":""},"children":[{"type":"element","tag":"code","props":{"__ignoreMap":""},"children":[{"type":"element","tag":"span","props":{"class":"line","line":1},"children":[{"type":"element","tag":"span","props":{"style":"--shiki-light:#0991B6;--shiki-default:#0991B6;--shiki-dark:#FF8F40"},"children":[{"type":"text","value":"function"}]},{"type":"element","tag":"span","props":{"style":"--shiki-light:#7EB233;--shiki-default:#7EB233;--shiki-dark:#FFB454"},"children":[{"type":"text","value":" findMostWord"}]},{"type":"element","tag":"span","props":{"style":"--shiki-light:#002339;--shiki-default:#002339;--shiki-dark:#BFBDB6"},"children":[{"type":"text","value":"("}]},{"type":"element","tag":"span","props":{"style":"--shiki-light:#B1108E;--shiki-default:#B1108E;--shiki-dark:#D2A6FF"},"children":[{"type":"text","value":"content"}]},{"type":"element","tag":"span","props":{"style":"--shiki-light:#002339;--shiki-default:#002339;--shiki-dark:#BFBDB6"},"children":[{"type":"text","value":") {\n"}]}]},{"type":"element","tag":"span","props":{"class":"line","line":2},"children":[{"type":"element","tag":"span","props":{"style":"--shiki-light:#357B42;--shiki-default:#357B42;--shiki-dark:#ACB6BF8C;--shiki-light-font-style:italic;--shiki-default-font-style:italic;--shiki-dark-font-style:italic"},"children":[{"type":"text","value":"  // 合法性判断\n"}]}]},{"type":"element","tag":"span","props":{"class":"line","line":3},"children":[{"type":"element","tag":"span","props":{"style":"--shiki-light:#7B30D0;--shiki-default:#7B30D0;--shiki-dark:#FF8F40"},"children":[{"type":"text","value":"  if"}]},{"type":"element","tag":"span","props":{"style":"--shiki-light:#002339;--shiki-default:#002339;--shiki-dark:#BFBDB6"},"children":[{"type":"text","value":" ("}]},{"type":"element","tag":"span","props":{"style":"--shiki-light:#7B30D0;--shiki-default:#7B30D0;--shiki-dark:#F29668"},"children":[{"type":"text","value":"!"}]},{"type":"element","tag":"span","props":{"style":"--shiki-light:#2F86D2;--shiki-default:#2F86D2;--shiki-dark:#BFBDB6"},"children":[{"type":"text","value":"content"}]},{"type":"element","tag":"span","props":{"style":"--shiki-light:#002339;--shiki-default:#002339;--shiki-dark:#BFBDB6"},"children":[{"type":"text","value":") "}]},{"type":"element","tag":"span","props":{"style":"--shiki-light:#7B30D0;--shiki-default:#7B30D0;--shiki-dark:#FF8F40"},"children":[{"type":"text","value":"return"}]},{"type":"element","tag":"span","props":{"style":"--shiki-light:#002339;--shiki-default:#002339;--shiki-dark:#BFBDB6B3"},"children":[{"type":"text","value":";\n"}]}]},{"type":"element","tag":"span","props":{"class":"line","line":4},"children":[{"type":"element","tag":"span","props":{"emptyLinePlaceholder":true},"children":[{"type":"text","value":"\n"}]}]},{"type":"element","tag":"span","props":{"class":"line","line":5},"children":[{"type":"element","tag":"span","props":{"style":"--shiki-light:#357B42;--shiki-default:#357B42;--shiki-dark:#ACB6BF8C;--shiki-light-font-style:italic;--shiki-default-font-style:italic;--shiki-dark-font-style:italic"},"children":[{"type":"text","value":"  // 参数处理\n"}]}]},{"type":"element","tag":"span","props":{"class":"line","line":6},"children":[{"type":"element","tag":"span","props":{"style":"--shiki-light:#2F86D2;--shiki-default:#2F86D2;--shiki-dark:#BFBDB6"},"children":[{"type":"text","value":"  content"}]},{"type":"element","tag":"span","props":{"style":"--shiki-light:#7B30D0;--shiki-default:#7B30D0;--shiki-dark:#F29668"},"children":[{"type":"text","value":" ="}]},{"type":"element","tag":"span","props":{"style":"--shiki-light:#2F86D2;--shiki-default:#2F86D2;--shiki-dark:#BFBDB6"},"children":[{"type":"text","value":" content"}]},{"type":"element","tag":"span","props":{"style":"--shiki-light:#002339;--shiki-default:#002339;--shiki-dark:#F29668"},"children":[{"type":"text","value":"."}]},{"type":"element","tag":"span","props":{"style":"--shiki-light:#7EB233;--shiki-default:#7EB233;--shiki-dark:#FFB454"},"children":[{"type":"text","value":"trim"}]},{"type":"element","tag":"span","props":{"style":"--shiki-light:#002339;--shiki-default:#002339;--shiki-dark:#BFBDB6"},"children":[{"type":"text","value":"()"}]},{"type":"element","tag":"span","props":{"style":"--shiki-light:#002339;--shiki-default:#002339;--shiki-dark:#F29668"},"children":[{"type":"text","value":"."}]},{"type":"element","tag":"span","props":{"style":"--shiki-light:#7EB233;--shiki-default:#7EB233;--shiki-dark:#FFB454"},"children":[{"type":"text","value":"toLowerCase"}]},{"type":"element","tag":"span","props":{"style":"--shiki-light:#002339;--shiki-default:#002339;--shiki-dark:#BFBDB6"},"children":[{"type":"text","value":"()"}]},{"type":"element","tag":"span","props":{"style":"--shiki-light:#002339;--shiki-default:#002339;--shiki-dark:#BFBDB6B3"},"children":[{"type":"text","value":";\n"}]}]},{"type":"element","tag":"span","props":{"class":"line","line":7},"children":[{"type":"element","tag":"span","props":{"emptyLinePlaceholder":true},"children":[{"type":"text","value":"\n"}]}]},{"type":"element","tag":"span","props":{"class":"line","line":8},"children":[{"type":"element","tag":"span","props":{"style":"--shiki-light:#0991B6;--shiki-default:#0991B6;--shiki-dark:#FF8F40"},"children":[{"type":"text","value":"  let"}]},{"type":"element","tag":"span","props":{"style":"--shiki-light:#2F86D2;--shiki-default:#2F86D2;--shiki-dark:#BFBDB6"},"children":[{"type":"text","value":" wordList"}]},{"type":"element","tag":"span","props":{"style":"--shiki-light:#7B30D0;--shiki-default:#7B30D0;--shiki-dark:#F29668"},"children":[{"type":"text","value":" ="}]},{"type":"element","tag":"span","props":{"style":"--shiki-light:#2F86D2;--shiki-default:#2F86D2;--shiki-dark:#BFBDB6"},"children":[{"type":"text","value":" content"}]},{"type":"element","tag":"span","props":{"style":"--shiki-light:#002339;--shiki-default:#002339;--shiki-dark:#F29668"},"children":[{"type":"text","value":"."}]},{"type":"element","tag":"span","props":{"style":"--shiki-light:#7EB233;--shiki-default:#7EB233;--shiki-dark:#FFB454"},"children":[{"type":"text","value":"match"}]},{"type":"element","tag":"span","props":{"style":"--shiki-light:#002339;--shiki-default:#002339;--shiki-dark:#BFBDB6"},"children":[{"type":"text","value":"("}]},{"type":"element","tag":"span","props":{"style":"--shiki-light:#A44185;--shiki-default:#A44185;--shiki-dark:#95E6CB"},"children":[{"type":"text","value":"/"}]},{"type":"element","tag":"span","props":{"style":"--shiki-light:#174781;--shiki-default:#174781;--shiki-dark:#95E6CB"},"children":[{"type":"text","value":"[a-z]"}]},{"type":"element","tag":"span","props":{"style":"--shiki-light:#7B30D0;--shiki-default:#7B30D0;--shiki-dark:#F29668"},"children":[{"type":"text","value":"+"}]},{"type":"element","tag":"span","props":{"style":"--shiki-light:#A44185;--shiki-default:#A44185;--shiki-dark:#95E6CB"},"children":[{"type":"text","value":"/"}]},{"type":"element","tag":"span","props":{"style":"--shiki-light:#7B30D0;--shiki-default:#7B30D0;--shiki-dark:#FF8F40"},"children":[{"type":"text","value":"g"}]},{"type":"element","tag":"span","props":{"style":"--shiki-light:#002339;--shiki-default:#002339;--shiki-dark:#BFBDB6"},"children":[{"type":"text","value":")"}]},{"type":"element","tag":"span","props":{"style":"--shiki-light:#002339;--shiki-default:#002339;--shiki-dark:#BFBDB6B3"},"children":[{"type":"text","value":";\n"}]}]},{"type":"element","tag":"span","props":{"class":"line","line":9},"children":[{"type":"element","tag":"span","props":{"style":"--shiki-light:#0991B6;--shiki-default:#0991B6;--shiki-dark:#FF8F40"},"children":[{"type":"text","value":"  let"}]},{"type":"element","tag":"span","props":{"style":"--shiki-light:#2F86D2;--shiki-default:#2F86D2;--shiki-dark:#BFBDB6"},"children":[{"type":"text","value":" visited"}]},{"type":"element","tag":"span","props":{"style":"--shiki-light:#7B30D0;--shiki-default:#7B30D0;--shiki-dark:#F29668"},"children":[{"type":"text","value":" ="}]},{"type":"element","tag":"span","props":{"style":"--shiki-light:#002339;--shiki-default:#002339;--shiki-dark:#BFBDB6"},"children":[{"type":"text","value":" []"}]},{"type":"element","tag":"span","props":{"style":"--shiki-light:#002339;--shiki-default:#002339;--shiki-dark:#BFBDB6B3"},"children":[{"type":"text","value":";\n"}]}]},{"type":"element","tag":"span","props":{"class":"line","line":10},"children":[{"type":"element","tag":"span","props":{"style":"--shiki-light:#0991B6;--shiki-default:#0991B6;--shiki-dark:#FF8F40"},"children":[{"type":"text","value":"  let"}]},{"type":"element","tag":"span","props":{"style":"--shiki-light:#2F86D2;--shiki-default:#2F86D2;--shiki-dark:#BFBDB6"},"children":[{"type":"text","value":" maxNum"}]},{"type":"element","tag":"span","props":{"style":"--shiki-light:#7B30D0;--shiki-default:#7B30D0;--shiki-dark:#F29668"},"children":[{"type":"text","value":" ="}]},{"type":"element","tag":"span","props":{"style":"--shiki-light:#174781;--shiki-default:#174781;--shiki-dark:#D2A6FF"},"children":[{"type":"text","value":" 0"}]},{"type":"element","tag":"span","props":{"style":"--shiki-light:#002339;--shiki-default:#002339;--shiki-dark:#BFBDB6B3"},"children":[{"type":"text","value":";\n"}]}]},{"type":"element","tag":"span","props":{"class":"line","line":11},"children":[{"type":"element","tag":"span","props":{"style":"--shiki-light:#0991B6;--shiki-default:#0991B6;--shiki-dark:#FF8F40"},"children":[{"type":"text","value":"  let"}]},{"type":"element","tag":"span","props":{"style":"--shiki-light:#2F86D2;--shiki-default:#2F86D2;--shiki-dark:#BFBDB6"},"children":[{"type":"text","value":" maxWord"}]},{"type":"element","tag":"span","props":{"style":"--shiki-light:#7B30D0;--shiki-default:#7B30D0;--shiki-dark:#F29668"},"children":[{"type":"text","value":" ="}]},{"type":"element","tag":"span","props":{"style":"--shiki-light:#A44185;--shiki-default:#A44185;--shiki-dark:#AAD94C"},"children":[{"type":"text","value":" \"\""}]},{"type":"element","tag":"span","props":{"style":"--shiki-light:#002339;--shiki-default:#002339;--shiki-dark:#BFBDB6B3"},"children":[{"type":"text","value":";\n"}]}]},{"type":"element","tag":"span","props":{"class":"line","line":12},"children":[{"type":"element","tag":"span","props":{"emptyLinePlaceholder":true},"children":[{"type":"text","value":"\n"}]}]},{"type":"element","tag":"span","props":{"class":"line","line":13},"children":[{"type":"element","tag":"span","props":{"style":"--shiki-light:#2F86D2;--shiki-default:#2F86D2;--shiki-dark:#BFBDB6"},"children":[{"type":"text","value":"  content"}]},{"type":"element","tag":"span","props":{"style":"--shiki-light:#7B30D0;--shiki-default:#7B30D0;--shiki-dark:#F29668"},"children":[{"type":"text","value":" ="}]},{"type":"element","tag":"span","props":{"style":"--shiki-light:#A44185;--shiki-default:#A44185;--shiki-dark:#AAD94C"},"children":[{"type":"text","value":" \" \""}]},{"type":"element","tag":"span","props":{"style":"--shiki-light:#7B30D0;--shiki-default:#7B30D0;--shiki-dark:#F29668"},"children":[{"type":"text","value":" +"}]},{"type":"element","tag":"span","props":{"style":"--shiki-light:#2F86D2;--shiki-default:#2F86D2;--shiki-dark:#BFBDB6"},"children":[{"type":"text","value":" wordList"}]},{"type":"element","tag":"span","props":{"style":"--shiki-light:#002339;--shiki-default:#002339;--shiki-dark:#F29668"},"children":[{"type":"text","value":"."}]},{"type":"element","tag":"span","props":{"style":"--shiki-light:#7EB233;--shiki-default:#7EB233;--shiki-dark:#FFB454"},"children":[{"type":"text","value":"join"}]},{"type":"element","tag":"span","props":{"style":"--shiki-light:#002339;--shiki-default:#002339;--shiki-dark:#BFBDB6"},"children":[{"type":"text","value":"("}]},{"type":"element","tag":"span","props":{"style":"--shiki-light:#A44185;--shiki-default:#A44185;--shiki-dark:#AAD94C"},"children":[{"type":"text","value":"\"  \""}]},{"type":"element","tag":"span","props":{"style":"--shiki-light:#002339;--shiki-default:#002339;--shiki-dark:#BFBDB6"},"children":[{"type":"text","value":") "}]},{"type":"element","tag":"span","props":{"style":"--shiki-light:#7B30D0;--shiki-default:#7B30D0;--shiki-dark:#F29668"},"children":[{"type":"text","value":"+"}]},{"type":"element","tag":"span","props":{"style":"--shiki-light:#A44185;--shiki-default:#A44185;--shiki-dark:#AAD94C"},"children":[{"type":"text","value":" \" \""}]},{"type":"element","tag":"span","props":{"style":"--shiki-light:#002339;--shiki-default:#002339;--shiki-dark:#BFBDB6B3"},"children":[{"type":"text","value":";\n"}]}]},{"type":"element","tag":"span","props":{"class":"line","line":14},"children":[{"type":"element","tag":"span","props":{"emptyLinePlaceholder":true},"children":[{"type":"text","value":"\n"}]}]},{"type":"element","tag":"span","props":{"class":"line","line":15},"children":[{"type":"element","tag":"span","props":{"style":"--shiki-light:#357B42;--shiki-default:#357B42;--shiki-dark:#ACB6BF8C;--shiki-light-font-style:italic;--shiki-default-font-style:italic;--shiki-dark-font-style:italic"},"children":[{"type":"text","value":"  // 遍历判断单词出现次数\n"}]}]},{"type":"element","tag":"span","props":{"class":"line","line":16},"children":[{"type":"element","tag":"span","props":{"style":"--shiki-light:#2F86D2;--shiki-default:#2F86D2;--shiki-dark:#BFBDB6"},"children":[{"type":"text","value":"  wordList"}]},{"type":"element","tag":"span","props":{"style":"--shiki-light:#002339;--shiki-default:#002339;--shiki-dark:#F29668"},"children":[{"type":"text","value":"."}]},{"type":"element","tag":"span","props":{"style":"--shiki-light:#7EB233;--shiki-default:#7EB233;--shiki-dark:#FFB454"},"children":[{"type":"text","value":"forEach"}]},{"type":"element","tag":"span","props":{"style":"--shiki-light:#002339;--shiki-default:#002339;--shiki-dark:#BFBDB6"},"children":[{"type":"text","value":"("}]},{"type":"element","tag":"span","props":{"style":"--shiki-light:#0991B6;--shiki-default:#0991B6;--shiki-dark:#FF8F40"},"children":[{"type":"text","value":"function"}]},{"type":"element","tag":"span","props":{"style":"--shiki-light:#002339;--shiki-default:#002339;--shiki-dark:#BFBDB6"},"children":[{"type":"text","value":" ("}]},{"type":"element","tag":"span","props":{"style":"--shiki-light:#B1108E;--shiki-default:#B1108E;--shiki-dark:#D2A6FF"},"children":[{"type":"text","value":"item"}]},{"type":"element","tag":"span","props":{"style":"--shiki-light:#002339;--shiki-default:#002339;--shiki-dark:#BFBDB6"},"children":[{"type":"text","value":") {\n"}]}]},{"type":"element","tag":"span","props":{"class":"line","line":17},"children":[{"type":"element","tag":"span","props":{"style":"--shiki-light:#7B30D0;--shiki-default:#7B30D0;--shiki-dark:#FF8F40"},"children":[{"type":"text","value":"    if"}]},{"type":"element","tag":"span","props":{"style":"--shiki-light:#002339;--shiki-default:#002339;--shiki-dark:#BFBDB6"},"children":[{"type":"text","value":" ("}]},{"type":"element","tag":"span","props":{"style":"--shiki-light:#2F86D2;--shiki-default:#2F86D2;--shiki-dark:#BFBDB6"},"children":[{"type":"text","value":"visited"}]},{"type":"element","tag":"span","props":{"style":"--shiki-light:#002339;--shiki-default:#002339;--shiki-dark:#F29668"},"children":[{"type":"text","value":"."}]},{"type":"element","tag":"span","props":{"style":"--shiki-light:#7EB233;--shiki-default:#7EB233;--shiki-dark:#FFB454"},"children":[{"type":"text","value":"indexOf"}]},{"type":"element","tag":"span","props":{"style":"--shiki-light:#002339;--shiki-default:#002339;--shiki-dark:#BFBDB6"},"children":[{"type":"text","value":"("}]},{"type":"element","tag":"span","props":{"style":"--shiki-light:#2F86D2;--shiki-default:#2F86D2;--shiki-dark:#BFBDB6"},"children":[{"type":"text","value":"item"}]},{"type":"element","tag":"span","props":{"style":"--shiki-light:#002339;--shiki-default:#002339;--shiki-dark:#BFBDB6"},"children":[{"type":"text","value":") "}]},{"type":"element","tag":"span","props":{"style":"--shiki-light:#7B30D0;--shiki-default:#7B30D0;--shiki-dark:#F29668"},"children":[{"type":"text","value":"<"}]},{"type":"element","tag":"span","props":{"style":"--shiki-light:#174781;--shiki-default:#174781;--shiki-dark:#D2A6FF"},"children":[{"type":"text","value":" 0"}]},{"type":"element","tag":"span","props":{"style":"--shiki-light:#002339;--shiki-default:#002339;--shiki-dark:#BFBDB6"},"children":[{"type":"text","value":") {\n"}]}]},{"type":"element","tag":"span","props":{"class":"line","line":18},"children":[{"type":"element","tag":"span","props":{"style":"--shiki-light:#357B42;--shiki-default:#357B42;--shiki-dark:#ACB6BF8C;--shiki-light-font-style:italic;--shiki-default-font-style:italic;--shiki-dark-font-style:italic"},"children":[{"type":"text","value":"      // 加入 visited\n"}]}]},{"type":"element","tag":"span","props":{"class":"line","line":19},"children":[{"type":"element","tag":"span","props":{"style":"--shiki-light:#2F86D2;--shiki-default:#2F86D2;--shiki-dark:#BFBDB6"},"children":[{"type":"text","value":"      visited"}]},{"type":"element","tag":"span","props":{"style":"--shiki-light:#002339;--shiki-default:#002339;--shiki-dark:#F29668"},"children":[{"type":"text","value":"."}]},{"type":"element","tag":"span","props":{"style":"--shiki-light:#7EB233;--shiki-default:#7EB233;--shiki-dark:#FFB454"},"children":[{"type":"text","value":"push"}]},{"type":"element","tag":"span","props":{"style":"--shiki-light:#002339;--shiki-default:#002339;--shiki-dark:#BFBDB6"},"children":[{"type":"text","value":"("}]},{"type":"element","tag":"span","props":{"style":"--shiki-light:#2F86D2;--shiki-default:#2F86D2;--shiki-dark:#BFBDB6"},"children":[{"type":"text","value":"item"}]},{"type":"element","tag":"span","props":{"style":"--shiki-light:#002339;--shiki-default:#002339;--shiki-dark:#BFBDB6"},"children":[{"type":"text","value":")"}]},{"type":"element","tag":"span","props":{"style":"--shiki-light:#002339;--shiki-default:#002339;--shiki-dark:#BFBDB6B3"},"children":[{"type":"text","value":";\n"}]}]},{"type":"element","tag":"span","props":{"class":"line","line":20},"children":[{"type":"element","tag":"span","props":{"emptyLinePlaceholder":true},"children":[{"type":"text","value":"\n"}]}]},{"type":"element","tag":"span","props":{"class":"line","line":21},"children":[{"type":"element","tag":"span","props":{"style":"--shiki-light:#0991B6;--shiki-default:#0991B6;--shiki-dark:#FF8F40"},"children":[{"type":"text","value":"      let"}]},{"type":"element","tag":"span","props":{"style":"--shiki-light:#2F86D2;--shiki-default:#2F86D2;--shiki-dark:#BFBDB6"},"children":[{"type":"text","value":" word"}]},{"type":"element","tag":"span","props":{"style":"--shiki-light:#7B30D0;--shiki-default:#7B30D0;--shiki-dark:#F29668"},"children":[{"type":"text","value":" ="}]},{"type":"element","tag":"span","props":{"style":"--shiki-light:#7B30D0;--shiki-default:#7B30D0;--shiki-dark:#F29668"},"children":[{"type":"text","value":" new"}]},{"type":"element","tag":"span","props":{"style":"--shiki-light:#7EB233;--shiki-default:#7EB233;--shiki-dark:#FFB454"},"children":[{"type":"text","value":" RegExp"}]},{"type":"element","tag":"span","props":{"style":"--shiki-light:#002339;--shiki-default:#002339;--shiki-dark:#BFBDB6"},"children":[{"type":"text","value":"("}]},{"type":"element","tag":"span","props":{"style":"--shiki-light:#A44185;--shiki-default:#A44185;--shiki-dark:#AAD94C"},"children":[{"type":"text","value":"\" \""}]},{"type":"element","tag":"span","props":{"style":"--shiki-light:#7B30D0;--shiki-default:#7B30D0;--shiki-dark:#F29668"},"children":[{"type":"text","value":" +"}]},{"type":"element","tag":"span","props":{"style":"--shiki-light:#2F86D2;--shiki-default:#2F86D2;--shiki-dark:#BFBDB6"},"children":[{"type":"text","value":" item"}]},{"type":"element","tag":"span","props":{"style":"--shiki-light:#7B30D0;--shiki-default:#7B30D0;--shiki-dark:#F29668"},"children":[{"type":"text","value":" +"}]},{"type":"element","tag":"span","props":{"style":"--shiki-light:#A44185;--shiki-default:#A44185;--shiki-dark:#AAD94C"},"children":[{"type":"text","value":" \" \""}]},{"type":"element","tag":"span","props":{"style":"--shiki-light:#002339;--shiki-default:#002339;--shiki-dark:#BFBDB6B3"},"children":[{"type":"text","value":","}]},{"type":"element","tag":"span","props":{"style":"--shiki-light:#A44185;--shiki-default:#A44185;--shiki-dark:#AAD94C"},"children":[{"type":"text","value":" \"g\""}]},{"type":"element","tag":"span","props":{"style":"--shiki-light:#002339;--shiki-default:#002339;--shiki-dark:#BFBDB6"},"children":[{"type":"text","value":")"}]},{"type":"element","tag":"span","props":{"style":"--shiki-light:#002339;--shiki-default:#002339;--shiki-dark:#BFBDB6B3"},"children":[{"type":"text","value":";\n"}]}]},{"type":"element","tag":"span","props":{"class":"line","line":22},"children":[{"type":"element","tag":"span","props":{"style":"--shiki-light:#0991B6;--shiki-default:#0991B6;--shiki-dark:#FF8F40"},"children":[{"type":"text","value":"      let"}]},{"type":"element","tag":"span","props":{"style":"--shiki-light:#2F86D2;--shiki-default:#2F86D2;--shiki-dark:#BFBDB6"},"children":[{"type":"text","value":" num"}]},{"type":"element","tag":"span","props":{"style":"--shiki-light:#7B30D0;--shiki-default:#7B30D0;--shiki-dark:#F29668"},"children":[{"type":"text","value":" ="}]},{"type":"element","tag":"span","props":{"style":"--shiki-light:#2F86D2;--shiki-default:#2F86D2;--shiki-dark:#BFBDB6"},"children":[{"type":"text","value":" content"}]},{"type":"element","tag":"span","props":{"style":"--shiki-light:#002339;--shiki-default:#002339;--shiki-dark:#F29668"},"children":[{"type":"text","value":"."}]},{"type":"element","tag":"span","props":{"style":"--shiki-light:#7EB233;--shiki-default:#7EB233;--shiki-dark:#FFB454"},"children":[{"type":"text","value":"match"}]},{"type":"element","tag":"span","props":{"style":"--shiki-light:#002339;--shiki-default:#002339;--shiki-dark:#BFBDB6"},"children":[{"type":"text","value":"("}]},{"type":"element","tag":"span","props":{"style":"--shiki-light:#2F86D2;--shiki-default:#2F86D2;--shiki-dark:#BFBDB6"},"children":[{"type":"text","value":"word"}]},{"type":"element","tag":"span","props":{"style":"--shiki-light:#002339;--shiki-default:#002339;--shiki-dark:#BFBDB6"},"children":[{"type":"text","value":")"}]},{"type":"element","tag":"span","props":{"style":"--shiki-light:#002339;--shiki-default:#002339;--shiki-dark:#F29668"},"children":[{"type":"text","value":"."}]},{"type":"element","tag":"span","props":{"style":"--shiki-light:#002339;--shiki-default:#002339;--shiki-dark:#BFBDB6"},"children":[{"type":"text","value":"length"}]},{"type":"element","tag":"span","props":{"style":"--shiki-light:#002339;--shiki-default:#002339;--shiki-dark:#BFBDB6B3"},"children":[{"type":"text","value":";\n"}]}]},{"type":"element","tag":"span","props":{"class":"line","line":23},"children":[{"type":"element","tag":"span","props":{"emptyLinePlaceholder":true},"children":[{"type":"text","value":"\n"}]}]},{"type":"element","tag":"span","props":{"class":"line","line":24},"children":[{"type":"element","tag":"span","props":{"style":"--shiki-light:#7B30D0;--shiki-default:#7B30D0;--shiki-dark:#FF8F40"},"children":[{"type":"text","value":"      if"}]},{"type":"element","tag":"span","props":{"style":"--shiki-light:#002339;--shiki-default:#002339;--shiki-dark:#BFBDB6"},"children":[{"type":"text","value":" ("}]},{"type":"element","tag":"span","props":{"style":"--shiki-light:#2F86D2;--shiki-default:#2F86D2;--shiki-dark:#BFBDB6"},"children":[{"type":"text","value":"num"}]},{"type":"element","tag":"span","props":{"style":"--shiki-light:#7B30D0;--shiki-default:#7B30D0;--shiki-dark:#F29668"},"children":[{"type":"text","value":" >"}]},{"type":"element","tag":"span","props":{"style":"--shiki-light:#2F86D2;--shiki-default:#2F86D2;--shiki-dark:#BFBDB6"},"children":[{"type":"text","value":" maxNum"}]},{"type":"element","tag":"span","props":{"style":"--shiki-light:#002339;--shiki-default:#002339;--shiki-dark:#BFBDB6"},"children":[{"type":"text","value":") {\n"}]}]},{"type":"element","tag":"span","props":{"class":"line","line":25},"children":[{"type":"element","tag":"span","props":{"style":"--shiki-light:#2F86D2;--shiki-default:#2F86D2;--shiki-dark:#BFBDB6"},"children":[{"type":"text","value":"        maxNum"}]},{"type":"element","tag":"span","props":{"style":"--shiki-light:#7B30D0;--shiki-default:#7B30D0;--shiki-dark:#F29668"},"children":[{"type":"text","value":" ="}]},{"type":"element","tag":"span","props":{"style":"--shiki-light:#2F86D2;--shiki-default:#2F86D2;--shiki-dark:#BFBDB6"},"children":[{"type":"text","value":" num"}]},{"type":"element","tag":"span","props":{"style":"--shiki-light:#002339;--shiki-default:#002339;--shiki-dark:#BFBDB6B3"},"children":[{"type":"text","value":";\n"}]}]},{"type":"element","tag":"span","props":{"class":"line","line":26},"children":[{"type":"element","tag":"span","props":{"style":"--shiki-light:#2F86D2;--shiki-default:#2F86D2;--shiki-dark:#BFBDB6"},"children":[{"type":"text","value":"        maxWord"}]},{"type":"element","tag":"span","props":{"style":"--shiki-light:#7B30D0;--shiki-default:#7B30D0;--shiki-dark:#F29668"},"children":[{"type":"text","value":" ="}]},{"type":"element","tag":"span","props":{"style":"--shiki-light:#2F86D2;--shiki-default:#2F86D2;--shiki-dark:#BFBDB6"},"children":[{"type":"text","value":" item"}]},{"type":"element","tag":"span","props":{"style":"--shiki-light:#002339;--shiki-default:#002339;--shiki-dark:#BFBDB6B3"},"children":[{"type":"text","value":";\n"}]}]},{"type":"element","tag":"span","props":{"class":"line","line":27},"children":[{"type":"element","tag":"span","props":{"style":"--shiki-light:#002339;--shiki-default:#002339;--shiki-dark:#BFBDB6"},"children":[{"type":"text","value":"      }\n"}]}]},{"type":"element","tag":"span","props":{"class":"line","line":28},"children":[{"type":"element","tag":"span","props":{"style":"--shiki-light:#002339;--shiki-default:#002339;--shiki-dark:#BFBDB6"},"children":[{"type":"text","value":"    }\n"}]}]},{"type":"element","tag":"span","props":{"class":"line","line":29},"children":[{"type":"element","tag":"span","props":{"style":"--shiki-light:#002339;--shiki-default:#002339;--shiki-dark:#BFBDB6"},"children":[{"type":"text","value":"  })"}]},{"type":"element","tag":"span","props":{"style":"--shiki-light:#002339;--shiki-default:#002339;--shiki-dark:#BFBDB6B3"},"children":[{"type":"text","value":";\n"}]}]},{"type":"element","tag":"span","props":{"class":"line","line":30},"children":[{"type":"element","tag":"span","props":{"emptyLinePlaceholder":true},"children":[{"type":"text","value":"\n"}]}]},{"type":"element","tag":"span","props":{"class":"line","line":31},"children":[{"type":"element","tag":"span","props":{"style":"--shiki-light:#7B30D0;--shiki-default:#7B30D0;--shiki-dark:#FF8F40"},"children":[{"type":"text","value":"  return"}]},{"type":"element","tag":"span","props":{"style":"--shiki-light:#2F86D2;--shiki-default:#2F86D2;--shiki-dark:#BFBDB6"},"children":[{"type":"text","value":" maxWord"}]},{"type":"element","tag":"span","props":{"style":"--shiki-light:#7B30D0;--shiki-default:#7B30D0;--shiki-dark:#F29668"},"children":[{"type":"text","value":" +"}]},{"type":"element","tag":"span","props":{"style":"--shiki-light:#A44185;--shiki-default:#A44185;--shiki-dark:#AAD94C"},"children":[{"type":"text","value":" \"  \""}]},{"type":"element","tag":"span","props":{"style":"--shiki-light:#7B30D0;--shiki-default:#7B30D0;--shiki-dark:#F29668"},"children":[{"type":"text","value":" +"}]},{"type":"element","tag":"span","props":{"style":"--shiki-light:#2F86D2;--shiki-default:#2F86D2;--shiki-dark:#BFBDB6"},"children":[{"type":"text","value":" maxNum"}]},{"type":"element","tag":"span","props":{"style":"--shiki-light:#002339;--shiki-default:#002339;--shiki-dark:#BFBDB6B3"},"children":[{"type":"text","value":";\n"}]}]},{"type":"element","tag":"span","props":{"class":"line","line":32},"children":[{"type":"element","tag":"span","props":{"style":"--shiki-light:#002339;--shiki-default:#002339;--shiki-dark:#BFBDB6"},"children":[{"type":"text","value":"}\n"}]}]}]}]},{"type":"element","tag":"style","props":{},"children":[{"type":"text","value":"html .light .shiki span {color: var(--shiki-light);background: var(--shiki-light-bg);font-style: var(--shiki-light-font-style);font-weight: var(--shiki-light-font-weight);text-decoration: var(--shiki-light-text-decoration);}html.light .shiki span {color: var(--shiki-light);background: var(--shiki-light-bg);font-style: var(--shiki-light-font-style);font-weight: var(--shiki-light-font-weight);text-decoration: var(--shiki-light-text-decoration);}html .default .shiki span {color: var(--shiki-default);background: var(--shiki-default-bg);font-style: var(--shiki-default-font-style);font-weight: var(--shiki-default-font-weight);text-decoration: var(--shiki-default-text-decoration);}html .shiki span {color: var(--shiki-default);background: var(--shiki-default-bg);font-style: var(--shiki-default-font-style);font-weight: var(--shiki-default-font-weight);text-decoration: var(--shiki-default-text-decoration);}html .dark .shiki span {color: var(--shiki-dark);background: var(--shiki-dark-bg);font-style: var(--shiki-dark-font-style);font-weight: var(--shiki-dark-font-weight);text-decoration: var(--shiki-dark-text-decoration);}html.dark .shiki span {color: var(--shiki-dark);background: var(--shiki-dark-bg);font-style: var(--shiki-dark-font-style);font-weight: var(--shiki-dark-font-weight);text-decoration: var(--shiki-dark-text-decoration);}"}]}],"toc":{"title":"","searchDepth":5,"depth":5,"links":[]}},"_type":"markdown","_id":"content:3.frontend-code-assessment:2.scene:most-frequent-characters-in-content.md","_source":"content","_file":"3.frontend-code-assessment/2.scene/most-frequent-characters-in-content.md","_extension":"md"}