{"_path":"/code-assessment/source/native-api/iterator","_dir":"native-api","_draft":false,"_partial":false,"_locale":"","title":"Iterator 迭代器","description":"","body":{"type":"root","children":[{"type":"element","tag":"h2","props":{"id":"实现迭代器函数"},"children":[{"type":"text","value":"实现迭代器函数"}]},{"type":"element","tag":"pre","props":{"className":"language-js shiki shiki-themes vitesse-light vitesse-light vitesse-dark","code":"/*\n * 这是一个手写的迭代器(Iterator)\n * 满足迭代器协议的对象。\n * 迭代器协议: 对象的 next 方法是一个无参函数，它返回一个对象，该对象拥有 done 和 value 两个属性：\n */\nvar it = makeIterator([\"a\", \"b\"]);\n\nit.next(); // { value: \"a\", done: false }\nit.next(); // { value: \"b\", done: false }\nit.next(); // { value: undefined, done: true }\n\nfunction makeIterator(array) {\n  var nextIndex = 0;\n  return {\n    next: function () {\n      return nextIndex < array.length\n        ? { value: array[nextIndex++], done: false }\n        : { value: undefined, done: true };\n    },\n  };\n}\n","language":"js","meta":"","style":""},"children":[{"type":"element","tag":"code","props":{"__ignoreMap":""},"children":[{"type":"element","tag":"span","props":{"class":"line","line":1},"children":[{"type":"element","tag":"span","props":{"style":"--shiki-light:#A0ADA0;--shiki-default:#A0ADA0;--shiki-dark:#758575DD"},"children":[{"type":"text","value":"/*\n"}]}]},{"type":"element","tag":"span","props":{"class":"line","line":2},"children":[{"type":"element","tag":"span","props":{"style":"--shiki-light:#A0ADA0;--shiki-default:#A0ADA0;--shiki-dark:#758575DD"},"children":[{"type":"text","value":" * 这是一个手写的迭代器(Iterator)\n"}]}]},{"type":"element","tag":"span","props":{"class":"line","line":3},"children":[{"type":"element","tag":"span","props":{"style":"--shiki-light:#A0ADA0;--shiki-default:#A0ADA0;--shiki-dark:#758575DD"},"children":[{"type":"text","value":" * 满足迭代器协议的对象。\n"}]}]},{"type":"element","tag":"span","props":{"class":"line","line":4},"children":[{"type":"element","tag":"span","props":{"style":"--shiki-light:#A0ADA0;--shiki-default:#A0ADA0;--shiki-dark:#758575DD"},"children":[{"type":"text","value":" * 迭代器协议: 对象的 next 方法是一个无参函数，它返回一个对象，该对象拥有 done 和 value 两个属性：\n"}]}]},{"type":"element","tag":"span","props":{"class":"line","line":5},"children":[{"type":"element","tag":"span","props":{"style":"--shiki-light:#A0ADA0;--shiki-default:#A0ADA0;--shiki-dark:#758575DD"},"children":[{"type":"text","value":" */\n"}]}]},{"type":"element","tag":"span","props":{"class":"line","line":6},"children":[{"type":"element","tag":"span","props":{"style":"--shiki-light:#AB5959;--shiki-default:#AB5959;--shiki-dark:#CB7676"},"children":[{"type":"text","value":"var"}]},{"type":"element","tag":"span","props":{"style":"--shiki-light:#B07D48;--shiki-default:#B07D48;--shiki-dark:#BD976A"},"children":[{"type":"text","value":" it"}]},{"type":"element","tag":"span","props":{"style":"--shiki-light:#999999;--shiki-default:#999999;--shiki-dark:#666666"},"children":[{"type":"text","value":" ="}]},{"type":"element","tag":"span","props":{"style":"--shiki-light:#59873A;--shiki-default:#59873A;--shiki-dark:#80A665"},"children":[{"type":"text","value":" makeIterator"}]},{"type":"element","tag":"span","props":{"style":"--shiki-light:#999999;--shiki-default:#999999;--shiki-dark:#666666"},"children":[{"type":"text","value":"(["}]},{"type":"element","tag":"span","props":{"style":"--shiki-light:#B5695999;--shiki-default:#B5695999;--shiki-dark:#C98A7D99"},"children":[{"type":"text","value":"\""}]},{"type":"element","tag":"span","props":{"style":"--shiki-light:#B56959;--shiki-default:#B56959;--shiki-dark:#C98A7D"},"children":[{"type":"text","value":"a"}]},{"type":"element","tag":"span","props":{"style":"--shiki-light:#B5695999;--shiki-default:#B5695999;--shiki-dark:#C98A7D99"},"children":[{"type":"text","value":"\""}]},{"type":"element","tag":"span","props":{"style":"--shiki-light:#999999;--shiki-default:#999999;--shiki-dark:#666666"},"children":[{"type":"text","value":","}]},{"type":"element","tag":"span","props":{"style":"--shiki-light:#B5695999;--shiki-default:#B5695999;--shiki-dark:#C98A7D99"},"children":[{"type":"text","value":" \""}]},{"type":"element","tag":"span","props":{"style":"--shiki-light:#B56959;--shiki-default:#B56959;--shiki-dark:#C98A7D"},"children":[{"type":"text","value":"b"}]},{"type":"element","tag":"span","props":{"style":"--shiki-light:#B5695999;--shiki-default:#B5695999;--shiki-dark:#C98A7D99"},"children":[{"type":"text","value":"\""}]},{"type":"element","tag":"span","props":{"style":"--shiki-light:#999999;--shiki-default:#999999;--shiki-dark:#666666"},"children":[{"type":"text","value":"]);\n"}]}]},{"type":"element","tag":"span","props":{"class":"line","line":7},"children":[{"type":"element","tag":"span","props":{"emptyLinePlaceholder":true},"children":[{"type":"text","value":"\n"}]}]},{"type":"element","tag":"span","props":{"class":"line","line":8},"children":[{"type":"element","tag":"span","props":{"style":"--shiki-light:#B07D48;--shiki-default:#B07D48;--shiki-dark:#BD976A"},"children":[{"type":"text","value":"it"}]},{"type":"element","tag":"span","props":{"style":"--shiki-light:#999999;--shiki-default:#999999;--shiki-dark:#666666"},"children":[{"type":"text","value":"."}]},{"type":"element","tag":"span","props":{"style":"--shiki-light:#59873A;--shiki-default:#59873A;--shiki-dark:#80A665"},"children":[{"type":"text","value":"next"}]},{"type":"element","tag":"span","props":{"style":"--shiki-light:#999999;--shiki-default:#999999;--shiki-dark:#666666"},"children":[{"type":"text","value":"();"}]},{"type":"element","tag":"span","props":{"style":"--shiki-light:#A0ADA0;--shiki-default:#A0ADA0;--shiki-dark:#758575DD"},"children":[{"type":"text","value":" // { value: \"a\", done: false }\n"}]}]},{"type":"element","tag":"span","props":{"class":"line","line":9},"children":[{"type":"element","tag":"span","props":{"style":"--shiki-light:#B07D48;--shiki-default:#B07D48;--shiki-dark:#BD976A"},"children":[{"type":"text","value":"it"}]},{"type":"element","tag":"span","props":{"style":"--shiki-light:#999999;--shiki-default:#999999;--shiki-dark:#666666"},"children":[{"type":"text","value":"."}]},{"type":"element","tag":"span","props":{"style":"--shiki-light:#59873A;--shiki-default:#59873A;--shiki-dark:#80A665"},"children":[{"type":"text","value":"next"}]},{"type":"element","tag":"span","props":{"style":"--shiki-light:#999999;--shiki-default:#999999;--shiki-dark:#666666"},"children":[{"type":"text","value":"();"}]},{"type":"element","tag":"span","props":{"style":"--shiki-light:#A0ADA0;--shiki-default:#A0ADA0;--shiki-dark:#758575DD"},"children":[{"type":"text","value":" // { value: \"b\", done: false }\n"}]}]},{"type":"element","tag":"span","props":{"class":"line","line":10},"children":[{"type":"element","tag":"span","props":{"style":"--shiki-light:#B07D48;--shiki-default:#B07D48;--shiki-dark:#BD976A"},"children":[{"type":"text","value":"it"}]},{"type":"element","tag":"span","props":{"style":"--shiki-light:#999999;--shiki-default:#999999;--shiki-dark:#666666"},"children":[{"type":"text","value":"."}]},{"type":"element","tag":"span","props":{"style":"--shiki-light:#59873A;--shiki-default:#59873A;--shiki-dark:#80A665"},"children":[{"type":"text","value":"next"}]},{"type":"element","tag":"span","props":{"style":"--shiki-light:#999999;--shiki-default:#999999;--shiki-dark:#666666"},"children":[{"type":"text","value":"();"}]},{"type":"element","tag":"span","props":{"style":"--shiki-light:#A0ADA0;--shiki-default:#A0ADA0;--shiki-dark:#758575DD"},"children":[{"type":"text","value":" // { value: undefined, done: true }\n"}]}]},{"type":"element","tag":"span","props":{"class":"line","line":11},"children":[{"type":"element","tag":"span","props":{"emptyLinePlaceholder":true},"children":[{"type":"text","value":"\n"}]}]},{"type":"element","tag":"span","props":{"class":"line","line":12},"children":[{"type":"element","tag":"span","props":{"style":"--shiki-light:#AB5959;--shiki-default:#AB5959;--shiki-dark:#CB7676"},"children":[{"type":"text","value":"function"}]},{"type":"element","tag":"span","props":{"style":"--shiki-light:#59873A;--shiki-default:#59873A;--shiki-dark:#80A665"},"children":[{"type":"text","value":" makeIterator"}]},{"type":"element","tag":"span","props":{"style":"--shiki-light:#999999;--shiki-default:#999999;--shiki-dark:#666666"},"children":[{"type":"text","value":"("}]},{"type":"element","tag":"span","props":{"style":"--shiki-light:#B07D48;--shiki-default:#B07D48;--shiki-dark:#BD976A"},"children":[{"type":"text","value":"array"}]},{"type":"element","tag":"span","props":{"style":"--shiki-light:#999999;--shiki-default:#999999;--shiki-dark:#666666"},"children":[{"type":"text","value":")"}]},{"type":"element","tag":"span","props":{"style":"--shiki-light:#999999;--shiki-default:#999999;--shiki-dark:#666666"},"children":[{"type":"text","value":" {\n"}]}]},{"type":"element","tag":"span","props":{"class":"line","line":13},"children":[{"type":"element","tag":"span","props":{"style":"--shiki-light:#AB5959;--shiki-default:#AB5959;--shiki-dark:#CB7676"},"children":[{"type":"text","value":"  var"}]},{"type":"element","tag":"span","props":{"style":"--shiki-light:#B07D48;--shiki-default:#B07D48;--shiki-dark:#BD976A"},"children":[{"type":"text","value":" nextIndex"}]},{"type":"element","tag":"span","props":{"style":"--shiki-light:#999999;--shiki-default:#999999;--shiki-dark:#666666"},"children":[{"type":"text","value":" ="}]},{"type":"element","tag":"span","props":{"style":"--shiki-light:#2F798A;--shiki-default:#2F798A;--shiki-dark:#4C9A91"},"children":[{"type":"text","value":" 0"}]},{"type":"element","tag":"span","props":{"style":"--shiki-light:#999999;--shiki-default:#999999;--shiki-dark:#666666"},"children":[{"type":"text","value":";\n"}]}]},{"type":"element","tag":"span","props":{"class":"line","line":14},"children":[{"type":"element","tag":"span","props":{"style":"--shiki-light:#1E754F;--shiki-default:#1E754F;--shiki-dark:#4D9375"},"children":[{"type":"text","value":"  return"}]},{"type":"element","tag":"span","props":{"style":"--shiki-light:#999999;--shiki-default:#999999;--shiki-dark:#666666"},"children":[{"type":"text","value":" {\n"}]}]},{"type":"element","tag":"span","props":{"class":"line","line":15},"children":[{"type":"element","tag":"span","props":{"style":"--shiki-light:#59873A;--shiki-default:#59873A;--shiki-dark:#80A665"},"children":[{"type":"text","value":"    next"}]},{"type":"element","tag":"span","props":{"style":"--shiki-light:#999999;--shiki-default:#999999;--shiki-dark:#666666"},"children":[{"type":"text","value":":"}]},{"type":"element","tag":"span","props":{"style":"--shiki-light:#AB5959;--shiki-default:#AB5959;--shiki-dark:#CB7676"},"children":[{"type":"text","value":" function"}]},{"type":"element","tag":"span","props":{"style":"--shiki-light:#999999;--shiki-default:#999999;--shiki-dark:#666666"},"children":[{"type":"text","value":" ()"}]},{"type":"element","tag":"span","props":{"style":"--shiki-light:#999999;--shiki-default:#999999;--shiki-dark:#666666"},"children":[{"type":"text","value":" {\n"}]}]},{"type":"element","tag":"span","props":{"class":"line","line":16},"children":[{"type":"element","tag":"span","props":{"style":"--shiki-light:#1E754F;--shiki-default:#1E754F;--shiki-dark:#4D9375"},"children":[{"type":"text","value":"      return"}]},{"type":"element","tag":"span","props":{"style":"--shiki-light:#B07D48;--shiki-default:#B07D48;--shiki-dark:#BD976A"},"children":[{"type":"text","value":" nextIndex"}]},{"type":"element","tag":"span","props":{"style":"--shiki-light:#999999;--shiki-default:#999999;--shiki-dark:#666666"},"children":[{"type":"text","value":" <"}]},{"type":"element","tag":"span","props":{"style":"--shiki-light:#B07D48;--shiki-default:#B07D48;--shiki-dark:#BD976A"},"children":[{"type":"text","value":" array"}]},{"type":"element","tag":"span","props":{"style":"--shiki-light:#999999;--shiki-default:#999999;--shiki-dark:#666666"},"children":[{"type":"text","value":"."}]},{"type":"element","tag":"span","props":{"style":"--shiki-light:#998418;--shiki-default:#998418;--shiki-dark:#B8A965"},"children":[{"type":"text","value":"length\n"}]}]},{"type":"element","tag":"span","props":{"class":"line","line":17},"children":[{"type":"element","tag":"span","props":{"style":"--shiki-light:#AB5959;--shiki-default:#AB5959;--shiki-dark:#CB7676"},"children":[{"type":"text","value":"        ?"}]},{"type":"element","tag":"span","props":{"style":"--shiki-light:#999999;--shiki-default:#999999;--shiki-dark:#666666"},"children":[{"type":"text","value":" {"}]},{"type":"element","tag":"span","props":{"style":"--shiki-light:#998418;--shiki-default:#998418;--shiki-dark:#B8A965"},"children":[{"type":"text","value":" value"}]},{"type":"element","tag":"span","props":{"style":"--shiki-light:#999999;--shiki-default:#999999;--shiki-dark:#666666"},"children":[{"type":"text","value":":"}]},{"type":"element","tag":"span","props":{"style":"--shiki-light:#B07D48;--shiki-default:#B07D48;--shiki-dark:#BD976A"},"children":[{"type":"text","value":" array"}]},{"type":"element","tag":"span","props":{"style":"--shiki-light:#999999;--shiki-default:#999999;--shiki-dark:#666666"},"children":[{"type":"text","value":"["}]},{"type":"element","tag":"span","props":{"style":"--shiki-light:#B07D48;--shiki-default:#B07D48;--shiki-dark:#BD976A"},"children":[{"type":"text","value":"nextIndex"}]},{"type":"element","tag":"span","props":{"style":"--shiki-light:#AB5959;--shiki-default:#AB5959;--shiki-dark:#CB7676"},"children":[{"type":"text","value":"++"}]},{"type":"element","tag":"span","props":{"style":"--shiki-light:#999999;--shiki-default:#999999;--shiki-dark:#666666"},"children":[{"type":"text","value":"],"}]},{"type":"element","tag":"span","props":{"style":"--shiki-light:#998418;--shiki-default:#998418;--shiki-dark:#B8A965"},"children":[{"type":"text","value":" done"}]},{"type":"element","tag":"span","props":{"style":"--shiki-light:#999999;--shiki-default:#999999;--shiki-dark:#666666"},"children":[{"type":"text","value":":"}]},{"type":"element","tag":"span","props":{"style":"--shiki-light:#1E754F;--shiki-default:#1E754F;--shiki-dark:#4D9375"},"children":[{"type":"text","value":" false"}]},{"type":"element","tag":"span","props":{"style":"--shiki-light:#999999;--shiki-default:#999999;--shiki-dark:#666666"},"children":[{"type":"text","value":" }\n"}]}]},{"type":"element","tag":"span","props":{"class":"line","line":18},"children":[{"type":"element","tag":"span","props":{"style":"--shiki-light:#AB5959;--shiki-default:#AB5959;--shiki-dark:#CB7676"},"children":[{"type":"text","value":"        :"}]},{"type":"element","tag":"span","props":{"style":"--shiki-light:#999999;--shiki-default:#999999;--shiki-dark:#666666"},"children":[{"type":"text","value":" {"}]},{"type":"element","tag":"span","props":{"style":"--shiki-light:#998418;--shiki-default:#998418;--shiki-dark:#B8A965"},"children":[{"type":"text","value":" value"}]},{"type":"element","tag":"span","props":{"style":"--shiki-light:#999999;--shiki-default:#999999;--shiki-dark:#666666"},"children":[{"type":"text","value":":"}]},{"type":"element","tag":"span","props":{"style":"--shiki-light:#AB5959;--shiki-default:#AB5959;--shiki-dark:#CB7676"},"children":[{"type":"text","value":" undefined"}]},{"type":"element","tag":"span","props":{"style":"--shiki-light:#999999;--shiki-default:#999999;--shiki-dark:#666666"},"children":[{"type":"text","value":","}]},{"type":"element","tag":"span","props":{"style":"--shiki-light:#998418;--shiki-default:#998418;--shiki-dark:#B8A965"},"children":[{"type":"text","value":" done"}]},{"type":"element","tag":"span","props":{"style":"--shiki-light:#999999;--shiki-default:#999999;--shiki-dark:#666666"},"children":[{"type":"text","value":":"}]},{"type":"element","tag":"span","props":{"style":"--shiki-light:#1E754F;--shiki-default:#1E754F;--shiki-dark:#4D9375"},"children":[{"type":"text","value":" true"}]},{"type":"element","tag":"span","props":{"style":"--shiki-light:#999999;--shiki-default:#999999;--shiki-dark:#666666"},"children":[{"type":"text","value":" };\n"}]}]},{"type":"element","tag":"span","props":{"class":"line","line":19},"children":[{"type":"element","tag":"span","props":{"style":"--shiki-light:#999999;--shiki-default:#999999;--shiki-dark:#666666"},"children":[{"type":"text","value":"    },\n"}]}]},{"type":"element","tag":"span","props":{"class":"line","line":20},"children":[{"type":"element","tag":"span","props":{"style":"--shiki-light:#999999;--shiki-default:#999999;--shiki-dark:#666666"},"children":[{"type":"text","value":"  };\n"}]}]},{"type":"element","tag":"span","props":{"class":"line","line":21},"children":[{"type":"element","tag":"span","props":{"style":"--shiki-light:#999999;--shiki-default:#999999;--shiki-dark:#666666"},"children":[{"type":"text","value":"}\n"}]}]}]}]},{"type":"element","tag":"h2","props":{"id":"可迭代的迭代器"},"children":[{"type":"text","value":"可迭代的迭代器"}]},{"type":"element","tag":"pre","props":{"className":"language-js shiki shiki-themes vitesse-light vitesse-light vitesse-dark","code":"/**\n * 使迭代器可迭代\n * makeIterator 函数生成的迭代器并没有实现可迭代协议\n * 所以不能在 for...of 等语法中使用。\n * 可以为该对象实现可迭代协议，在 [Symbol.iterator] 函数中返回该迭代器自身\n * 从新名了下函数名称 createIterator\n */\nfunction createIterator(array) {\n  var nextIndex = 0;\n  return {\n    next: function () {\n      return nextIndex < array.length\n        ? { value: array[nextIndex++], done: false }\n        : { value: undefined, done: true };\n    },\n    [Symbol.iterator]: function () {\n      console.log(\"返回的迭代器:\", this);\n      return this; // 注意这里是对象调用模式，this 指向的就是上层的对象，迭代器\n    },\n  };\n}\n\nvar iterator = createIterator([1, 2, 3]);\nconsole.log(...iterator);\n","language":"js","meta":"","style":""},"children":[{"type":"element","tag":"code","props":{"__ignoreMap":""},"children":[{"type":"element","tag":"span","props":{"class":"line","line":1},"children":[{"type":"element","tag":"span","props":{"style":"--shiki-light:#A0ADA0;--shiki-default:#A0ADA0;--shiki-dark:#758575DD"},"children":[{"type":"text","value":"/**\n"}]}]},{"type":"element","tag":"span","props":{"class":"line","line":2},"children":[{"type":"element","tag":"span","props":{"style":"--shiki-light:#A0ADA0;--shiki-default:#A0ADA0;--shiki-dark:#758575DD"},"children":[{"type":"text","value":" * 使迭代器可迭代\n"}]}]},{"type":"element","tag":"span","props":{"class":"line","line":3},"children":[{"type":"element","tag":"span","props":{"style":"--shiki-light:#A0ADA0;--shiki-default:#A0ADA0;--shiki-dark:#758575DD"},"children":[{"type":"text","value":" * makeIterator 函数生成的迭代器并没有实现可迭代协议\n"}]}]},{"type":"element","tag":"span","props":{"class":"line","line":4},"children":[{"type":"element","tag":"span","props":{"style":"--shiki-light:#A0ADA0;--shiki-default:#A0ADA0;--shiki-dark:#758575DD"},"children":[{"type":"text","value":" * 所以不能在 for...of 等语法中使用。\n"}]}]},{"type":"element","tag":"span","props":{"class":"line","line":5},"children":[{"type":"element","tag":"span","props":{"style":"--shiki-light:#A0ADA0;--shiki-default:#A0ADA0;--shiki-dark:#758575DD"},"children":[{"type":"text","value":" * 可以为该对象实现可迭代协议，在 [Symbol.iterator] 函数中返回该迭代器自身\n"}]}]},{"type":"element","tag":"span","props":{"class":"line","line":6},"children":[{"type":"element","tag":"span","props":{"style":"--shiki-light:#A0ADA0;--shiki-default:#A0ADA0;--shiki-dark:#758575DD"},"children":[{"type":"text","value":" * 从新名了下函数名称 createIterator\n"}]}]},{"type":"element","tag":"span","props":{"class":"line","line":7},"children":[{"type":"element","tag":"span","props":{"style":"--shiki-light:#A0ADA0;--shiki-default:#A0ADA0;--shiki-dark:#758575DD"},"children":[{"type":"text","value":" */\n"}]}]},{"type":"element","tag":"span","props":{"class":"line","line":8},"children":[{"type":"element","tag":"span","props":{"style":"--shiki-light:#AB5959;--shiki-default:#AB5959;--shiki-dark:#CB7676"},"children":[{"type":"text","value":"function"}]},{"type":"element","tag":"span","props":{"style":"--shiki-light:#59873A;--shiki-default:#59873A;--shiki-dark:#80A665"},"children":[{"type":"text","value":" createIterator"}]},{"type":"element","tag":"span","props":{"style":"--shiki-light:#999999;--shiki-default:#999999;--shiki-dark:#666666"},"children":[{"type":"text","value":"("}]},{"type":"element","tag":"span","props":{"style":"--shiki-light:#B07D48;--shiki-default:#B07D48;--shiki-dark:#BD976A"},"children":[{"type":"text","value":"array"}]},{"type":"element","tag":"span","props":{"style":"--shiki-light:#999999;--shiki-default:#999999;--shiki-dark:#666666"},"children":[{"type":"text","value":")"}]},{"type":"element","tag":"span","props":{"style":"--shiki-light:#999999;--shiki-default:#999999;--shiki-dark:#666666"},"children":[{"type":"text","value":" {\n"}]}]},{"type":"element","tag":"span","props":{"class":"line","line":9},"children":[{"type":"element","tag":"span","props":{"style":"--shiki-light:#AB5959;--shiki-default:#AB5959;--shiki-dark:#CB7676"},"children":[{"type":"text","value":"  var"}]},{"type":"element","tag":"span","props":{"style":"--shiki-light:#B07D48;--shiki-default:#B07D48;--shiki-dark:#BD976A"},"children":[{"type":"text","value":" nextIndex"}]},{"type":"element","tag":"span","props":{"style":"--shiki-light:#999999;--shiki-default:#999999;--shiki-dark:#666666"},"children":[{"type":"text","value":" ="}]},{"type":"element","tag":"span","props":{"style":"--shiki-light:#2F798A;--shiki-default:#2F798A;--shiki-dark:#4C9A91"},"children":[{"type":"text","value":" 0"}]},{"type":"element","tag":"span","props":{"style":"--shiki-light:#999999;--shiki-default:#999999;--shiki-dark:#666666"},"children":[{"type":"text","value":";\n"}]}]},{"type":"element","tag":"span","props":{"class":"line","line":10},"children":[{"type":"element","tag":"span","props":{"style":"--shiki-light:#1E754F;--shiki-default:#1E754F;--shiki-dark:#4D9375"},"children":[{"type":"text","value":"  return"}]},{"type":"element","tag":"span","props":{"style":"--shiki-light:#999999;--shiki-default:#999999;--shiki-dark:#666666"},"children":[{"type":"text","value":" {\n"}]}]},{"type":"element","tag":"span","props":{"class":"line","line":11},"children":[{"type":"element","tag":"span","props":{"style":"--shiki-light:#59873A;--shiki-default:#59873A;--shiki-dark:#80A665"},"children":[{"type":"text","value":"    next"}]},{"type":"element","tag":"span","props":{"style":"--shiki-light:#999999;--shiki-default:#999999;--shiki-dark:#666666"},"children":[{"type":"text","value":":"}]},{"type":"element","tag":"span","props":{"style":"--shiki-light:#AB5959;--shiki-default:#AB5959;--shiki-dark:#CB7676"},"children":[{"type":"text","value":" function"}]},{"type":"element","tag":"span","props":{"style":"--shiki-light:#999999;--shiki-default:#999999;--shiki-dark:#666666"},"children":[{"type":"text","value":" ()"}]},{"type":"element","tag":"span","props":{"style":"--shiki-light:#999999;--shiki-default:#999999;--shiki-dark:#666666"},"children":[{"type":"text","value":" {\n"}]}]},{"type":"element","tag":"span","props":{"class":"line","line":12},"children":[{"type":"element","tag":"span","props":{"style":"--shiki-light:#1E754F;--shiki-default:#1E754F;--shiki-dark:#4D9375"},"children":[{"type":"text","value":"      return"}]},{"type":"element","tag":"span","props":{"style":"--shiki-light:#B07D48;--shiki-default:#B07D48;--shiki-dark:#BD976A"},"children":[{"type":"text","value":" nextIndex"}]},{"type":"element","tag":"span","props":{"style":"--shiki-light:#999999;--shiki-default:#999999;--shiki-dark:#666666"},"children":[{"type":"text","value":" <"}]},{"type":"element","tag":"span","props":{"style":"--shiki-light:#B07D48;--shiki-default:#B07D48;--shiki-dark:#BD976A"},"children":[{"type":"text","value":" array"}]},{"type":"element","tag":"span","props":{"style":"--shiki-light:#999999;--shiki-default:#999999;--shiki-dark:#666666"},"children":[{"type":"text","value":"."}]},{"type":"element","tag":"span","props":{"style":"--shiki-light:#998418;--shiki-default:#998418;--shiki-dark:#B8A965"},"children":[{"type":"text","value":"length\n"}]}]},{"type":"element","tag":"span","props":{"class":"line","line":13},"children":[{"type":"element","tag":"span","props":{"style":"--shiki-light:#AB5959;--shiki-default:#AB5959;--shiki-dark:#CB7676"},"children":[{"type":"text","value":"        ?"}]},{"type":"element","tag":"span","props":{"style":"--shiki-light:#999999;--shiki-default:#999999;--shiki-dark:#666666"},"children":[{"type":"text","value":" {"}]},{"type":"element","tag":"span","props":{"style":"--shiki-light:#998418;--shiki-default:#998418;--shiki-dark:#B8A965"},"children":[{"type":"text","value":" value"}]},{"type":"element","tag":"span","props":{"style":"--shiki-light:#999999;--shiki-default:#999999;--shiki-dark:#666666"},"children":[{"type":"text","value":":"}]},{"type":"element","tag":"span","props":{"style":"--shiki-light:#B07D48;--shiki-default:#B07D48;--shiki-dark:#BD976A"},"children":[{"type":"text","value":" array"}]},{"type":"element","tag":"span","props":{"style":"--shiki-light:#999999;--shiki-default:#999999;--shiki-dark:#666666"},"children":[{"type":"text","value":"["}]},{"type":"element","tag":"span","props":{"style":"--shiki-light:#B07D48;--shiki-default:#B07D48;--shiki-dark:#BD976A"},"children":[{"type":"text","value":"nextIndex"}]},{"type":"element","tag":"span","props":{"style":"--shiki-light:#AB5959;--shiki-default:#AB5959;--shiki-dark:#CB7676"},"children":[{"type":"text","value":"++"}]},{"type":"element","tag":"span","props":{"style":"--shiki-light:#999999;--shiki-default:#999999;--shiki-dark:#666666"},"children":[{"type":"text","value":"],"}]},{"type":"element","tag":"span","props":{"style":"--shiki-light:#998418;--shiki-default:#998418;--shiki-dark:#B8A965"},"children":[{"type":"text","value":" done"}]},{"type":"element","tag":"span","props":{"style":"--shiki-light:#999999;--shiki-default:#999999;--shiki-dark:#666666"},"children":[{"type":"text","value":":"}]},{"type":"element","tag":"span","props":{"style":"--shiki-light:#1E754F;--shiki-default:#1E754F;--shiki-dark:#4D9375"},"children":[{"type":"text","value":" false"}]},{"type":"element","tag":"span","props":{"style":"--shiki-light:#999999;--shiki-default:#999999;--shiki-dark:#666666"},"children":[{"type":"text","value":" }\n"}]}]},{"type":"element","tag":"span","props":{"class":"line","line":14},"children":[{"type":"element","tag":"span","props":{"style":"--shiki-light:#AB5959;--shiki-default:#AB5959;--shiki-dark:#CB7676"},"children":[{"type":"text","value":"        :"}]},{"type":"element","tag":"span","props":{"style":"--shiki-light:#999999;--shiki-default:#999999;--shiki-dark:#666666"},"children":[{"type":"text","value":" {"}]},{"type":"element","tag":"span","props":{"style":"--shiki-light:#998418;--shiki-default:#998418;--shiki-dark:#B8A965"},"children":[{"type":"text","value":" value"}]},{"type":"element","tag":"span","props":{"style":"--shiki-light:#999999;--shiki-default:#999999;--shiki-dark:#666666"},"children":[{"type":"text","value":":"}]},{"type":"element","tag":"span","props":{"style":"--shiki-light:#AB5959;--shiki-default:#AB5959;--shiki-dark:#CB7676"},"children":[{"type":"text","value":" undefined"}]},{"type":"element","tag":"span","props":{"style":"--shiki-light:#999999;--shiki-default:#999999;--shiki-dark:#666666"},"children":[{"type":"text","value":","}]},{"type":"element","tag":"span","props":{"style":"--shiki-light:#998418;--shiki-default:#998418;--shiki-dark:#B8A965"},"children":[{"type":"text","value":" done"}]},{"type":"element","tag":"span","props":{"style":"--shiki-light:#999999;--shiki-default:#999999;--shiki-dark:#666666"},"children":[{"type":"text","value":":"}]},{"type":"element","tag":"span","props":{"style":"--shiki-light:#1E754F;--shiki-default:#1E754F;--shiki-dark:#4D9375"},"children":[{"type":"text","value":" true"}]},{"type":"element","tag":"span","props":{"style":"--shiki-light:#999999;--shiki-default:#999999;--shiki-dark:#666666"},"children":[{"type":"text","value":" };\n"}]}]},{"type":"element","tag":"span","props":{"class":"line","line":15},"children":[{"type":"element","tag":"span","props":{"style":"--shiki-light:#999999;--shiki-default:#999999;--shiki-dark:#666666"},"children":[{"type":"text","value":"    },\n"}]}]},{"type":"element","tag":"span","props":{"class":"line","line":16},"children":[{"type":"element","tag":"span","props":{"style":"--shiki-light:#999999;--shiki-default:#999999;--shiki-dark:#666666"},"children":[{"type":"text","value":"    ["}]},{"type":"element","tag":"span","props":{"style":"--shiki-light:#B07D48;--shiki-default:#B07D48;--shiki-dark:#BD976A"},"children":[{"type":"text","value":"Symbol"}]},{"type":"element","tag":"span","props":{"style":"--shiki-light:#999999;--shiki-default:#999999;--shiki-dark:#666666"},"children":[{"type":"text","value":"."}]},{"type":"element","tag":"span","props":{"style":"--shiki-light:#B07D48;--shiki-default:#B07D48;--shiki-dark:#BD976A"},"children":[{"type":"text","value":"iterator"}]},{"type":"element","tag":"span","props":{"style":"--shiki-light:#999999;--shiki-default:#999999;--shiki-dark:#666666"},"children":[{"type":"text","value":"]:"}]},{"type":"element","tag":"span","props":{"style":"--shiki-light:#AB5959;--shiki-default:#AB5959;--shiki-dark:#CB7676"},"children":[{"type":"text","value":" function"}]},{"type":"element","tag":"span","props":{"style":"--shiki-light:#999999;--shiki-default:#999999;--shiki-dark:#666666"},"children":[{"type":"text","value":" ()"}]},{"type":"element","tag":"span","props":{"style":"--shiki-light:#999999;--shiki-default:#999999;--shiki-dark:#666666"},"children":[{"type":"text","value":" {\n"}]}]},{"type":"element","tag":"span","props":{"class":"line","line":17},"children":[{"type":"element","tag":"span","props":{"style":"--shiki-light:#B07D48;--shiki-default:#B07D48;--shiki-dark:#BD976A"},"children":[{"type":"text","value":"      console"}]},{"type":"element","tag":"span","props":{"style":"--shiki-light:#999999;--shiki-default:#999999;--shiki-dark:#666666"},"children":[{"type":"text","value":"."}]},{"type":"element","tag":"span","props":{"style":"--shiki-light:#59873A;--shiki-default:#59873A;--shiki-dark:#80A665"},"children":[{"type":"text","value":"log"}]},{"type":"element","tag":"span","props":{"style":"--shiki-light:#999999;--shiki-default:#999999;--shiki-dark:#666666"},"children":[{"type":"text","value":"("}]},{"type":"element","tag":"span","props":{"style":"--shiki-light:#B5695999;--shiki-default:#B5695999;--shiki-dark:#C98A7D99"},"children":[{"type":"text","value":"\""}]},{"type":"element","tag":"span","props":{"style":"--shiki-light:#B56959;--shiki-default:#B56959;--shiki-dark:#C98A7D"},"children":[{"type":"text","value":"返回的迭代器:"}]},{"type":"element","tag":"span","props":{"style":"--shiki-light:#B5695999;--shiki-default:#B5695999;--shiki-dark:#C98A7D99"},"children":[{"type":"text","value":"\""}]},{"type":"element","tag":"span","props":{"style":"--shiki-light:#999999;--shiki-default:#999999;--shiki-dark:#666666"},"children":[{"type":"text","value":","}]},{"type":"element","tag":"span","props":{"style":"--shiki-light:#A65E2B;--shiki-default:#A65E2B;--shiki-dark:#C99076"},"children":[{"type":"text","value":" this"}]},{"type":"element","tag":"span","props":{"style":"--shiki-light:#999999;--shiki-default:#999999;--shiki-dark:#666666"},"children":[{"type":"text","value":");\n"}]}]},{"type":"element","tag":"span","props":{"class":"line","line":18},"children":[{"type":"element","tag":"span","props":{"style":"--shiki-light:#1E754F;--shiki-default:#1E754F;--shiki-dark:#4D9375"},"children":[{"type":"text","value":"      return"}]},{"type":"element","tag":"span","props":{"style":"--shiki-light:#A65E2B;--shiki-default:#A65E2B;--shiki-dark:#C99076"},"children":[{"type":"text","value":" this"}]},{"type":"element","tag":"span","props":{"style":"--shiki-light:#999999;--shiki-default:#999999;--shiki-dark:#666666"},"children":[{"type":"text","value":";"}]},{"type":"element","tag":"span","props":{"style":"--shiki-light:#A0ADA0;--shiki-default:#A0ADA0;--shiki-dark:#758575DD"},"children":[{"type":"text","value":" // 注意这里是对象调用模式，this 指向的就是上层的对象，迭代器\n"}]}]},{"type":"element","tag":"span","props":{"class":"line","line":19},"children":[{"type":"element","tag":"span","props":{"style":"--shiki-light:#999999;--shiki-default:#999999;--shiki-dark:#666666"},"children":[{"type":"text","value":"    },\n"}]}]},{"type":"element","tag":"span","props":{"class":"line","line":20},"children":[{"type":"element","tag":"span","props":{"style":"--shiki-light:#999999;--shiki-default:#999999;--shiki-dark:#666666"},"children":[{"type":"text","value":"  };\n"}]}]},{"type":"element","tag":"span","props":{"class":"line","line":21},"children":[{"type":"element","tag":"span","props":{"style":"--shiki-light:#999999;--shiki-default:#999999;--shiki-dark:#666666"},"children":[{"type":"text","value":"}\n"}]}]},{"type":"element","tag":"span","props":{"class":"line","line":22},"children":[{"type":"element","tag":"span","props":{"emptyLinePlaceholder":true},"children":[{"type":"text","value":"\n"}]}]},{"type":"element","tag":"span","props":{"class":"line","line":23},"children":[{"type":"element","tag":"span","props":{"style":"--shiki-light:#AB5959;--shiki-default:#AB5959;--shiki-dark:#CB7676"},"children":[{"type":"text","value":"var"}]},{"type":"element","tag":"span","props":{"style":"--shiki-light:#B07D48;--shiki-default:#B07D48;--shiki-dark:#BD976A"},"children":[{"type":"text","value":" iterator"}]},{"type":"element","tag":"span","props":{"style":"--shiki-light:#999999;--shiki-default:#999999;--shiki-dark:#666666"},"children":[{"type":"text","value":" ="}]},{"type":"element","tag":"span","props":{"style":"--shiki-light:#59873A;--shiki-default:#59873A;--shiki-dark:#80A665"},"children":[{"type":"text","value":" createIterator"}]},{"type":"element","tag":"span","props":{"style":"--shiki-light:#999999;--shiki-default:#999999;--shiki-dark:#666666"},"children":[{"type":"text","value":"(["}]},{"type":"element","tag":"span","props":{"style":"--shiki-light:#2F798A;--shiki-default:#2F798A;--shiki-dark:#4C9A91"},"children":[{"type":"text","value":"1"}]},{"type":"element","tag":"span","props":{"style":"--shiki-light:#999999;--shiki-default:#999999;--shiki-dark:#666666"},"children":[{"type":"text","value":","}]},{"type":"element","tag":"span","props":{"style":"--shiki-light:#2F798A;--shiki-default:#2F798A;--shiki-dark:#4C9A91"},"children":[{"type":"text","value":" 2"}]},{"type":"element","tag":"span","props":{"style":"--shiki-light:#999999;--shiki-default:#999999;--shiki-dark:#666666"},"children":[{"type":"text","value":","}]},{"type":"element","tag":"span","props":{"style":"--shiki-light:#2F798A;--shiki-default:#2F798A;--shiki-dark:#4C9A91"},"children":[{"type":"text","value":" 3"}]},{"type":"element","tag":"span","props":{"style":"--shiki-light:#999999;--shiki-default:#999999;--shiki-dark:#666666"},"children":[{"type":"text","value":"]);\n"}]}]},{"type":"element","tag":"span","props":{"class":"line","line":24},"children":[{"type":"element","tag":"span","props":{"style":"--shiki-light:#B07D48;--shiki-default:#B07D48;--shiki-dark:#BD976A"},"children":[{"type":"text","value":"console"}]},{"type":"element","tag":"span","props":{"style":"--shiki-light:#999999;--shiki-default:#999999;--shiki-dark:#666666"},"children":[{"type":"text","value":"."}]},{"type":"element","tag":"span","props":{"style":"--shiki-light:#59873A;--shiki-default:#59873A;--shiki-dark:#80A665"},"children":[{"type":"text","value":"log"}]},{"type":"element","tag":"span","props":{"style":"--shiki-light:#999999;--shiki-default:#999999;--shiki-dark:#666666"},"children":[{"type":"text","value":"(..."}]},{"type":"element","tag":"span","props":{"style":"--shiki-light:#B07D48;--shiki-default:#B07D48;--shiki-dark:#BD976A"},"children":[{"type":"text","value":"iterator"}]},{"type":"element","tag":"span","props":{"style":"--shiki-light:#999999;--shiki-default:#999999;--shiki-dark:#666666"},"children":[{"type":"text","value":");\n"}]}]}]}]},{"type":"element","tag":"style","props":{},"children":[{"type":"text","value":"html .light .shiki span {color: var(--shiki-light);background: var(--shiki-light-bg);font-style: var(--shiki-light-font-style);font-weight: var(--shiki-light-font-weight);text-decoration: var(--shiki-light-text-decoration);}html.light .shiki span {color: var(--shiki-light);background: var(--shiki-light-bg);font-style: var(--shiki-light-font-style);font-weight: var(--shiki-light-font-weight);text-decoration: var(--shiki-light-text-decoration);}html .default .shiki span {color: var(--shiki-default);background: var(--shiki-default-bg);font-style: var(--shiki-default-font-style);font-weight: var(--shiki-default-font-weight);text-decoration: var(--shiki-default-text-decoration);}html .shiki span {color: var(--shiki-default);background: var(--shiki-default-bg);font-style: var(--shiki-default-font-style);font-weight: var(--shiki-default-font-weight);text-decoration: var(--shiki-default-text-decoration);}html .dark .shiki span {color: var(--shiki-dark);background: var(--shiki-dark-bg);font-style: var(--shiki-dark-font-style);font-weight: var(--shiki-dark-font-weight);text-decoration: var(--shiki-dark-text-decoration);}html.dark .shiki span {color: var(--shiki-dark);background: var(--shiki-dark-bg);font-style: var(--shiki-dark-font-style);font-weight: var(--shiki-dark-font-weight);text-decoration: var(--shiki-dark-text-decoration);}"}]}],"toc":{"title":"","searchDepth":5,"depth":5,"links":[{"id":"实现迭代器函数","depth":2,"text":"实现迭代器函数"},{"id":"可迭代的迭代器","depth":2,"text":"可迭代的迭代器"}]}},"_type":"markdown","_id":"content:3.code-assessment:1.source:1.native-api:7.iterator.md","_source":"content","_file":"3.code-assessment/1.source/1.native-api/7.iterator.md","_extension":"md"}